{
  "source": "baidu",
  "updatedAt": "2026-03-29T10:56:40.793Z",
  "count": 20,
  "items": [
    {
      "rank": 1,
      "title": "源清流清 向上向善",
      "url": "https://www.baidu.com/s?wd=%E6%BA%90%E6%B8%85%E6%B5%81%E6%B8%85+%E5%90%91%E4%B8%8A%E5%90%91%E5%96%84&sa=fyb_news&rsv_dl=fyb_news",
      "meta": "7904100"
    },
    {
      "rank": 2,
      "title": "台媒热议：无人、无人还是无人",
      "url": "https://www.baidu.com/s?wd=%E5%8F%B0%E5%AA%92%E7%83%AD%E8%AE%AE%EF%BC%9A%E6%97%A0%E4%BA%BA%E3%80%81%E6%97%A0%E4%BA%BA%E8%BF%98%E6%98%AF%E6%97%A0%E4%BA%BA&sa=fyb_news&rsv_dl=fyb_news",
      "meta": "7808563"
    },
    {
      "rank": 3,
      "title": "中学教材成海外旅游“接头暗号”",
      "url": "https://www.baidu.com/s?wd=%E4%B8%AD%E5%AD%A6%E6%95%99%E6%9D%90%E6%88%90%E6%B5%B7%E5%A4%96%E6%97%85%E6%B8%B8%E2%80%9C%E6%8E%A5%E5%A4%B4%E6%9A%97%E5%8F%B7%E2%80%9D&sa=fyb_news&rsv_dl=fyb_news",
      "meta": "7712288"
    },
    {
      "rank": 4,
      "title": "一辆“聪明”的车是如何“炼”成的",
      "url": "https://www.baidu.com/s?wd=%E4%B8%80%E8%BE%86%E2%80%9C%E8%81%AA%E6%98%8E%E2%80%9D%E7%9A%84%E8%BD%A6%E6%98%AF%E5%A6%82%E4%BD%95%E2%80%9C%E7%82%BC%E2%80%9D%E6%88%90%E7%9A%84&sa=fyb_news&rsv_dl=fyb_news",
      "meta": "7616777"
    },
    {
      "rank": 5,
      "title": "内存条价格崩了",
      "url": "https://www.baidu.com/s?wd=%E5%86%85%E5%AD%98%E6%9D%A1%E4%BB%B7%E6%A0%BC%E5%B4%A9%E4%BA%86&sa=fyb_news&rsv_dl=fyb_news",
      "meta": "7520277"
    },
    {
      "rank": 6,
      "title": "澳门世界杯国乒抽签结果出炉",
      "url": "https://www.baidu.com/s?wd=%E6%BE%B3%E9%97%A8%E4%B8%96%E7%95%8C%E6%9D%AF%E5%9B%BD%E4%B9%92%E6%8A%BD%E7%AD%BE%E7%BB%93%E6%9E%9C%E5%87%BA%E7%82%89&sa=fyb_news&rsv_dl=fyb_news",
      "meta": "7429349"
    },
    {
      "rank": 7,
      "title": "摆拍“打网约车遭司机辱骂”者被罚",
      "url": "https://www.baidu.com/s?wd=%E6%91%86%E6%8B%8D%E2%80%9C%E6%89%93%E7%BD%91%E7%BA%A6%E8%BD%A6%E9%81%AD%E5%8F%B8%E6%9C%BA%E8%BE%B1%E9%AA%82%E2%80%9D%E8%80%85%E8%A2%AB%E7%BD%9A&sa=fyb_news&rsv_dl=fyb_news",
      "meta": "7333741"
    },
    {
      "rank": 8,
      "title": "伊朗公布击毁美军E-3预警机卫星图",
      "url": "https://www.baidu.com/s?wd=%E4%BC%8A%E6%9C%97%E5%85%AC%E5%B8%83%E5%87%BB%E6%AF%81%E7%BE%8E%E5%86%9BE-3%E9%A2%84%E8%AD%A6%E6%9C%BA%E5%8D%AB%E6%98%9F%E5%9B%BE&sa=fyb_news&rsv_dl=fyb_news",
      "meta": "7231484"
    },
    {
      "rank": 9,
      "title": "“周末情侣”为啥愈发普遍",
      "url": "https://www.baidu.com/s?wd=%E2%80%9C%E5%91%A8%E6%9C%AB%E6%83%85%E4%BE%A3%E2%80%9D%E4%B8%BA%E5%95%A5%E6%84%88%E5%8F%91%E6%99%AE%E9%81%8D&sa=fyb_news&rsv_dl=fyb_news",
      "meta": "7143077"
    },
    {
      "rank": 10,
      "title": "胡塞入局 红海告急",
      "url": "https://www.baidu.com/s?wd=%E8%83%A1%E5%A1%9E%E5%85%A5%E5%B1%80+%E7%BA%A2%E6%B5%B7%E5%91%8A%E6%80%A5&sa=fyb_news&rsv_dl=fyb_news",
      "meta": "7041851"
    },
    {
      "rank": 11,
      "title": "日本抗议者高喊中国对不起",
      "url": "https://www.baidu.com/s?wd=%E6%97%A5%E6%9C%AC%E6%8A%97%E8%AE%AE%E8%80%85%E9%AB%98%E5%96%8A%E4%B8%AD%E5%9B%BD%E5%AF%B9%E4%B8%8D%E8%B5%B7&sa=fyb_news&rsv_dl=fyb_news",
      "meta": "6943313"
    },
    {
      "rank": 12,
      "title": "宁波一女孩接迷药传单晕倒系谣言",
      "url": "https://www.baidu.com/s?wd=%E5%AE%81%E6%B3%A2%E4%B8%80%E5%A5%B3%E5%AD%A9%E6%8E%A5%E8%BF%B7%E8%8D%AF%E4%BC%A0%E5%8D%95%E6%99%95%E5%80%92%E7%B3%BB%E8%B0%A3%E8%A8%80&sa=fyb_news&rsv_dl=fyb_news",
      "meta": "6848223"
    },
    {
      "rank": 13,
      "title": "李荣浩公开指责单依纯：强行侵权",
      "url": "https://www.baidu.com/s?wd=%E6%9D%8E%E8%8D%A3%E6%B5%A9%E5%85%AC%E5%BC%80%E6%8C%87%E8%B4%A3%E5%8D%95%E4%BE%9D%E7%BA%AF%EF%BC%9A%E5%BC%BA%E8%A1%8C%E4%BE%B5%E6%9D%83&sa=fyb_news&rsv_dl=fyb_news",
      "meta": "6761258"
    },
    {
      "rank": 14,
      "title": "女子在家被流浪狗咬伤3天后狗死了",
      "url": "https://www.baidu.com/s?wd=%E5%A5%B3%E5%AD%90%E5%9C%A8%E5%AE%B6%E8%A2%AB%E6%B5%81%E6%B5%AA%E7%8B%97%E5%92%AC%E4%BC%A43%E5%A4%A9%E5%90%8E%E7%8B%97%E6%AD%BB%E4%BA%86&sa=fyb_news&rsv_dl=fyb_news",
      "meta": "6657410"
    },
    {
      "rank": 15,
      "title": "全美3000多城市举行大规模抗议活动",
      "url": "https://www.baidu.com/s?wd=%E5%85%A8%E7%BE%8E3000%E5%A4%9A%E5%9F%8E%E5%B8%82%E4%B8%BE%E8%A1%8C%E5%A4%A7%E8%A7%84%E6%A8%A1%E6%8A%97%E8%AE%AE%E6%B4%BB%E5%8A%A8&sa=fyb_news&rsv_dl=fyb_news",
      "meta": "6573280"
    },
    {
      "rank": 16,
      "title": "单依纯向李荣浩道歉",
      "url": "https://www.baidu.com/s?wd=%E5%8D%95%E4%BE%9D%E7%BA%AF%E5%90%91%E6%9D%8E%E8%8D%A3%E6%B5%A9%E9%81%93%E6%AD%89&sa=fyb_news&rsv_dl=fyb_news",
      "meta": "6467456"
    },
    {
      "rank": 17,
      "title": "夫妻房产留给长子长孙遭两女儿反对",
      "url": "https://www.baidu.com/s?wd=%E5%A4%AB%E5%A6%BB%E6%88%BF%E4%BA%A7%E7%95%99%E7%BB%99%E9%95%BF%E5%AD%90%E9%95%BF%E5%AD%99%E9%81%AD%E4%B8%A4%E5%A5%B3%E5%84%BF%E5%8F%8D%E5%AF%B9&sa=fyb_news&rsv_dl=fyb_news",
      "meta": "6375010"
    },
    {
      "rank": 18,
      "title": "胡塞武装“参战” 对战局有何影响",
      "url": "https://www.baidu.com/s?wd=%E8%83%A1%E5%A1%9E%E6%AD%A6%E8%A3%85%E2%80%9C%E5%8F%82%E6%88%98%E2%80%9D+%E5%AF%B9%E6%88%98%E5%B1%80%E6%9C%89%E4%BD%95%E5%BD%B1%E5%93%8D&sa=fyb_news&rsv_dl=fyb_news",
      "meta": "6284801"
    },
    {
      "rank": 19,
      "title": "50岁何润东翻红 涨粉近100万",
      "url": "https://www.baidu.com/s?wd=50%E5%B2%81%E4%BD%95%E6%B6%A6%E4%B8%9C%E7%BF%BB%E7%BA%A2+%E6%B6%A8%E7%B2%89%E8%BF%91100%E4%B8%87&sa=fyb_news&rsv_dl=fyb_news",
      "meta": "6187655"
    },
    {
      "rank": 20,
      "title": "单依纯曾回应被调侃报复李荣浩：是爱",
      "url": "https://www.baidu.com/s?wd=%E5%8D%95%E4%BE%9D%E7%BA%AF%E6%9B%BE%E5%9B%9E%E5%BA%94%E8%A2%AB%E8%B0%83%E4%BE%83%E6%8A%A5%E5%A4%8D%E6%9D%8E%E8%8D%A3%E6%B5%A9%EF%BC%9A%E6%98%AF%E7%88%B1&sa=fyb_news&rsv_dl=fyb_news",
      "meta": "6082489"
    }
  ]
}
