{
  "source": "baidu",
  "updatedAt": "2026-05-27T12:28:12.754Z",
  "count": 20,
  "items": [
    {
      "rank": 1,
      "title": "“铁杆友谊”彰显中国外交的鲜明底色",
      "url": "https://www.baidu.com/s?wd=%E2%80%9C%E9%93%81%E6%9D%86%E5%8F%8B%E8%B0%8A%E2%80%9D%E5%BD%B0%E6%98%BE%E4%B8%AD%E5%9B%BD%E5%A4%96%E4%BA%A4%E7%9A%84%E9%B2%9C%E6%98%8E%E5%BA%95%E8%89%B2&sa=fyb_news&rsv_dl=fyb_news",
      "meta": "7904177"
    },
    {
      "rank": 2,
      "title": "教育部：这类学历不予认证",
      "url": "https://www.baidu.com/s?wd=%E6%95%99%E8%82%B2%E9%83%A8%EF%BC%9A%E8%BF%99%E7%B1%BB%E5%AD%A6%E5%8E%86%E4%B8%8D%E4%BA%88%E8%AE%A4%E8%AF%81&sa=fyb_news&rsv_dl=fyb_news",
      "meta": "7809257"
    },
    {
      "rank": 3,
      "title": "国台办发言人憋不住笑了：理屈才词穷",
      "url": "https://www.baidu.com/s?wd=%E5%9B%BD%E5%8F%B0%E5%8A%9E%E5%8F%91%E8%A8%80%E4%BA%BA%E6%86%8B%E4%B8%8D%E4%BD%8F%E7%AC%91%E4%BA%86%EF%BC%9A%E7%90%86%E5%B1%88%E6%89%8D%E8%AF%8D%E7%A9%B7&sa=fyb_news&rsv_dl=fyb_news",
      "meta": "7712409"
    },
    {
      "rank": 4,
      "title": "中国制造何以频频“爆单”",
      "url": "https://www.baidu.com/s?wd=%E4%B8%AD%E5%9B%BD%E5%88%B6%E9%80%A0%E4%BD%95%E4%BB%A5%E9%A2%91%E9%A2%91%E2%80%9C%E7%88%86%E5%8D%95%E2%80%9D&sa=fyb_news&rsv_dl=fyb_news",
      "meta": "7618164"
    },
    {
      "rank": 5,
      "title": "户口以后没那么重要了",
      "url": "https://www.baidu.com/s?wd=%E6%88%B7%E5%8F%A3%E4%BB%A5%E5%90%8E%E6%B2%A1%E9%82%A3%E4%B9%88%E9%87%8D%E8%A6%81%E4%BA%86&sa=fyb_news&rsv_dl=fyb_news",
      "meta": "7522793"
    },
    {
      "rank": 6,
      "title": "“外科医生为什么不撸串？”",
      "url": "https://www.baidu.com/s?wd=%E2%80%9C%E5%A4%96%E7%A7%91%E5%8C%BB%E7%94%9F%E4%B8%BA%E4%BB%80%E4%B9%88%E4%B8%8D%E6%92%B8%E4%B8%B2%EF%BC%9F%E2%80%9D&sa=fyb_news&rsv_dl=fyb_news",
      "meta": "7428626"
    },
    {
      "rank": 7,
      "title": "暴雨淹了家 夫妻俩1个玩手机1个补觉",
      "url": "https://www.baidu.com/s?wd=%E6%9A%B4%E9%9B%A8%E6%B7%B9%E4%BA%86%E5%AE%B6+%E5%A4%AB%E5%A6%BB%E4%BF%A91%E4%B8%AA%E7%8E%A9%E6%89%8B%E6%9C%BA1%E4%B8%AA%E8%A1%A5%E8%A7%89&sa=fyb_news&rsv_dl=fyb_news",
      "meta": "7332019"
    },
    {
      "rank": 8,
      "title": "终于见到“一蓑烟雨任平生”的实物",
      "url": "https://www.baidu.com/s?wd=%E7%BB%88%E4%BA%8E%E8%A7%81%E5%88%B0%E2%80%9C%E4%B8%80%E8%93%91%E7%83%9F%E9%9B%A8%E4%BB%BB%E5%B9%B3%E7%94%9F%E2%80%9D%E7%9A%84%E5%AE%9E%E7%89%A9&sa=fyb_news&rsv_dl=fyb_news",
      "meta": "7235343"
    },
    {
      "rank": 9,
      "title": "孙俪拍戏后眼睛血管破裂 医生提醒",
      "url": "https://www.baidu.com/s?wd=%E5%AD%99%E4%BF%AA%E6%8B%8D%E6%88%8F%E5%90%8E%E7%9C%BC%E7%9D%9B%E8%A1%80%E7%AE%A1%E7%A0%B4%E8%A3%82+%E5%8C%BB%E7%94%9F%E6%8F%90%E9%86%92&sa=fyb_news&rsv_dl=fyb_news",
      "meta": "7141235"
    },
    {
      "rank": 10,
      "title": "用儿子1万5压岁钱“抄底”炒股亏了",
      "url": "https://www.baidu.com/s?wd=%E7%94%A8%E5%84%BF%E5%AD%901%E4%B8%875%E5%8E%8B%E5%B2%81%E9%92%B1%E2%80%9C%E6%8A%84%E5%BA%95%E2%80%9D%E7%82%92%E8%82%A1%E4%BA%8F%E4%BA%86&sa=fyb_news&rsv_dl=fyb_news",
      "meta": "7045205"
    },
    {
      "rank": 11,
      "title": "记者暗访杭州地下助孕机构被打骨折",
      "url": "https://www.baidu.com/s?wd=%E8%AE%B0%E8%80%85%E6%9A%97%E8%AE%BF%E6%9D%AD%E5%B7%9E%E5%9C%B0%E4%B8%8B%E5%8A%A9%E5%AD%95%E6%9C%BA%E6%9E%84%E8%A2%AB%E6%89%93%E9%AA%A8%E6%8A%98&sa=fyb_news&rsv_dl=fyb_news",
      "meta": "6944763"
    },
    {
      "rank": 12,
      "title": "“成都试点育儿补贴延到6岁”不实",
      "url": "https://www.baidu.com/s?wd=%E2%80%9C%E6%88%90%E9%83%BD%E8%AF%95%E7%82%B9%E8%82%B2%E5%84%BF%E8%A1%A5%E8%B4%B4%E5%BB%B6%E5%88%B06%E5%B2%81%E2%80%9D%E4%B8%8D%E5%AE%9E&sa=fyb_news&rsv_dl=fyb_news",
      "meta": "6852552"
    },
    {
      "rank": 13,
      "title": "空调并不是开26度最省电",
      "url": "https://www.baidu.com/s?wd=%E7%A9%BA%E8%B0%83%E5%B9%B6%E4%B8%8D%E6%98%AF%E5%BC%8026%E5%BA%A6%E6%9C%80%E7%9C%81%E7%94%B5&sa=fyb_news&rsv_dl=fyb_news",
      "meta": "6761244"
    },
    {
      "rank": 14,
      "title": "欧洲热到失控",
      "url": "https://www.baidu.com/s?wd=%E6%AC%A7%E6%B4%B2%E7%83%AD%E5%88%B0%E5%A4%B1%E6%8E%A7&sa=fyb_news&rsv_dl=fyb_news",
      "meta": "6560945"
    },
    {
      "rank": 15,
      "title": "阿里员工十三薪将并入年终奖",
      "url": "https://www.baidu.com/s?wd=%E9%98%BF%E9%87%8C%E5%91%98%E5%B7%A5%E5%8D%81%E4%B8%89%E8%96%AA%E5%B0%86%E5%B9%B6%E5%85%A5%E5%B9%B4%E7%BB%88%E5%A5%96&sa=fyb_news&rsv_dl=fyb_news",
      "meta": "6466347"
    },
    {
      "rank": 16,
      "title": "深圳南坪快速火灾原因确认 官方通报",
      "url": "https://www.baidu.com/s?wd=%E6%B7%B1%E5%9C%B3%E5%8D%97%E5%9D%AA%E5%BF%AB%E9%80%9F%E7%81%AB%E7%81%BE%E5%8E%9F%E5%9B%A0%E7%A1%AE%E8%AE%A4+%E5%AE%98%E6%96%B9%E9%80%9A%E6%8A%A5&sa=fyb_news&rsv_dl=fyb_news",
      "meta": "6375430"
    },
    {
      "rank": 17,
      "title": "员工多次加班至凌晨 公司奖励100元",
      "url": "https://www.baidu.com/s?wd=%E5%91%98%E5%B7%A5%E5%A4%9A%E6%AC%A1%E5%8A%A0%E7%8F%AD%E8%87%B3%E5%87%8C%E6%99%A8+%E5%85%AC%E5%8F%B8%E5%A5%96%E5%8A%B1100%E5%85%83&sa=fyb_news&rsv_dl=fyb_news",
      "meta": "6276964"
    },
    {
      "rank": 18,
      "title": "印度高温 自来水高达51摄氏度",
      "url": "https://www.baidu.com/s?wd=%E5%8D%B0%E5%BA%A6%E9%AB%98%E6%B8%A9+%E8%87%AA%E6%9D%A5%E6%B0%B4%E9%AB%98%E8%BE%BE51%E6%91%84%E6%B0%8F%E5%BA%A6&sa=fyb_news&rsv_dl=fyb_news",
      "meta": "6085453"
    },
    {
      "rank": 19,
      "title": "江西省委常委李伟被查",
      "url": "https://www.baidu.com/s?wd=%E6%B1%9F%E8%A5%BF%E7%9C%81%E5%A7%94%E5%B8%B8%E5%A7%94%E6%9D%8E%E4%BC%9F%E8%A2%AB%E6%9F%A5&sa=fyb_news&rsv_dl=fyb_news",
      "meta": "5998236"
    },
    {
      "rank": 20,
      "title": "536分捡漏上北大学生打算读博",
      "url": "https://www.baidu.com/s?wd=536%E5%88%86%E6%8D%A1%E6%BC%8F%E4%B8%8A%E5%8C%97%E5%A4%A7%E5%AD%A6%E7%94%9F%E6%89%93%E7%AE%97%E8%AF%BB%E5%8D%9A&sa=fyb_news&rsv_dl=fyb_news",
      "meta": "5886438"
    }
  ]
}
