{
  "source": "baidu",
  "updatedAt": "2026-04-02T19:53:28.633Z",
  "count": 20,
  "items": [
    {
      "rank": 1,
      "title": "足迹里的政绩观",
      "url": "https://www.baidu.com/s?wd=%E8%B6%B3%E8%BF%B9%E9%87%8C%E7%9A%84%E6%94%BF%E7%BB%A9%E8%A7%82&sa=fyb_news&rsv_dl=fyb_news",
      "meta": "7904897"
    },
    {
      "rank": 2,
      "title": "人民日报：彻查优思益一案 斩断一链",
      "url": "https://www.baidu.com/s?wd=%E4%BA%BA%E6%B0%91%E6%97%A5%E6%8A%A5%EF%BC%9A%E5%BD%BB%E6%9F%A5%E4%BC%98%E6%80%9D%E7%9B%8A%E4%B8%80%E6%A1%88+%E6%96%A9%E6%96%AD%E4%B8%80%E9%93%BE&sa=fyb_news&rsv_dl=fyb_news",
      "meta": "7808801"
    },
    {
      "rank": 3,
      "title": "海警被走私艇冲撞牺牲 执法画面公开",
      "url": "https://www.baidu.com/s?wd=%E6%B5%B7%E8%AD%A6%E8%A2%AB%E8%B5%B0%E7%A7%81%E8%89%87%E5%86%B2%E6%92%9E%E7%89%BA%E7%89%B2+%E6%89%A7%E6%B3%95%E7%94%BB%E9%9D%A2%E5%85%AC%E5%BC%80&sa=fyb_news&rsv_dl=fyb_news",
      "meta": "7713905"
    },
    {
      "rank": 4,
      "title": "中国把数据中心搬进大海",
      "url": "https://www.baidu.com/s?wd=%E4%B8%AD%E5%9B%BD%E6%8A%8A%E6%95%B0%E6%8D%AE%E4%B8%AD%E5%BF%83%E6%90%AC%E8%BF%9B%E5%A4%A7%E6%B5%B7&sa=fyb_news&rsv_dl=fyb_news",
      "meta": "7616223"
    },
    {
      "rank": 5,
      "title": "国务院任免国家工作人员",
      "url": "https://www.baidu.com/s?wd=%E5%9B%BD%E5%8A%A1%E9%99%A2%E4%BB%BB%E5%85%8D%E5%9B%BD%E5%AE%B6%E5%B7%A5%E4%BD%9C%E4%BA%BA%E5%91%98&sa=fyb_news&rsv_dl=fyb_news",
      "meta": "7522673"
    },
    {
      "rank": 6,
      "title": "上海6只军犬退役面向社会招募领养人",
      "url": "https://www.baidu.com/s?wd=%E4%B8%8A%E6%B5%B76%E5%8F%AA%E5%86%9B%E7%8A%AC%E9%80%80%E5%BD%B9%E9%9D%A2%E5%90%91%E7%A4%BE%E4%BC%9A%E6%8B%9B%E5%8B%9F%E9%A2%86%E5%85%BB%E4%BA%BA&sa=fyb_news&rsv_dl=fyb_news",
      "meta": "7429047"
    },
    {
      "rank": 7,
      "title": "伊朗一特种部队指挥官身亡",
      "url": "https://www.baidu.com/s?wd=%E4%BC%8A%E6%9C%97%E4%B8%80%E7%89%B9%E7%A7%8D%E9%83%A8%E9%98%9F%E6%8C%87%E6%8C%A5%E5%AE%98%E8%BA%AB%E4%BA%A1&sa=fyb_news&rsv_dl=fyb_news",
      "meta": "7333092"
    },
    {
      "rank": 8,
      "title": "孙颖莎击败蒯曼晋级世界杯女单8强",
      "url": "https://www.baidu.com/s?wd=%E5%AD%99%E9%A2%96%E8%8E%8E%E5%87%BB%E8%B4%A5%E8%92%AF%E6%9B%BC%E6%99%8B%E7%BA%A7%E4%B8%96%E7%95%8C%E6%9D%AF%E5%A5%B3%E5%8D%958%E5%BC%BA&sa=fyb_news&rsv_dl=fyb_news",
      "meta": "7236815"
    },
    {
      "rank": 9,
      "title": "美国重返月球为何只绕不登",
      "url": "https://www.baidu.com/s?wd=%E7%BE%8E%E5%9B%BD%E9%87%8D%E8%BF%94%E6%9C%88%E7%90%83%E4%B8%BA%E4%BD%95%E5%8F%AA%E7%BB%95%E4%B8%8D%E7%99%BB&sa=fyb_news&rsv_dl=fyb_news",
      "meta": "7139436"
    },
    {
      "rank": 10,
      "title": "三部门约谈抖音、淘天、小红书",
      "url": "https://www.baidu.com/s?wd=%E4%B8%89%E9%83%A8%E9%97%A8%E7%BA%A6%E8%B0%88%E6%8A%96%E9%9F%B3%E3%80%81%E6%B7%98%E5%A4%A9%E3%80%81%E5%B0%8F%E7%BA%A2%E4%B9%A6&sa=fyb_news&rsv_dl=fyb_news",
      "meta": "7040418"
    },
    {
      "rank": 11,
      "title": "美载人绕月飞船升空后马桶出现故障",
      "url": "https://www.baidu.com/s?wd=%E7%BE%8E%E8%BD%BD%E4%BA%BA%E7%BB%95%E6%9C%88%E9%A3%9E%E8%88%B9%E5%8D%87%E7%A9%BA%E5%90%8E%E9%A9%AC%E6%A1%B6%E5%87%BA%E7%8E%B0%E6%95%85%E9%9A%9C&sa=fyb_news&rsv_dl=fyb_news",
      "meta": "6944201"
    },
    {
      "rank": 12,
      "title": "“严查后排安全带新规出台”不实",
      "url": "https://www.baidu.com/s?wd=%E2%80%9C%E4%B8%A5%E6%9F%A5%E5%90%8E%E6%8E%92%E5%AE%89%E5%85%A8%E5%B8%A6%E6%96%B0%E8%A7%84%E5%87%BA%E5%8F%B0%E2%80%9D%E4%B8%8D%E5%AE%9E&sa=fyb_news&rsv_dl=fyb_news",
      "meta": "6850866"
    },
    {
      "rank": 13,
      "title": "向华强曝短剧投200万赚7000万",
      "url": "https://www.baidu.com/s?wd=%E5%90%91%E5%8D%8E%E5%BC%BA%E6%9B%9D%E7%9F%AD%E5%89%A7%E6%8A%95200%E4%B8%87%E8%B5%9A7000%E4%B8%87&sa=fyb_news&rsv_dl=fyb_news",
      "meta": "6751222"
    },
    {
      "rank": 14,
      "title": "张雪谈为何用自己名字命名摩托车",
      "url": "https://www.baidu.com/s?wd=%E5%BC%A0%E9%9B%AA%E8%B0%88%E4%B8%BA%E4%BD%95%E7%94%A8%E8%87%AA%E5%B7%B1%E5%90%8D%E5%AD%97%E5%91%BD%E5%90%8D%E6%91%A9%E6%89%98%E8%BD%A6&sa=fyb_news&rsv_dl=fyb_news",
      "meta": "6655740"
    },
    {
      "rank": 15,
      "title": "王毅同德国外长瓦德富尔通电话",
      "url": "https://www.baidu.com/s?wd=%E7%8E%8B%E6%AF%85%E5%90%8C%E5%BE%B7%E5%9B%BD%E5%A4%96%E9%95%BF%E7%93%A6%E5%BE%B7%E5%AF%8C%E5%B0%94%E9%80%9A%E7%94%B5%E8%AF%9D&sa=fyb_news&rsv_dl=fyb_news",
      "meta": "6567451"
    },
    {
      "rank": 16,
      "title": "与辉同行回应带货优思益：全额退款",
      "url": "https://www.baidu.com/s?wd=%E4%B8%8E%E8%BE%89%E5%90%8C%E8%A1%8C%E5%9B%9E%E5%BA%94%E5%B8%A6%E8%B4%A7%E4%BC%98%E6%80%9D%E7%9B%8A%EF%BC%9A%E5%85%A8%E9%A2%9D%E9%80%80%E6%AC%BE&sa=fyb_news&rsv_dl=fyb_news",
      "meta": "6477064"
    },
    {
      "rank": 17,
      "title": "曾带货优思益 李若彤明道等致歉",
      "url": "https://www.baidu.com/s?wd=%E6%9B%BE%E5%B8%A6%E8%B4%A7%E4%BC%98%E6%80%9D%E7%9B%8A+%E6%9D%8E%E8%8B%A5%E5%BD%A4%E6%98%8E%E9%81%93%E7%AD%89%E8%87%B4%E6%AD%89&sa=fyb_news&rsv_dl=fyb_news",
      "meta": "6367721"
    },
    {
      "rank": 18,
      "title": "老人酒后泡澡死亡 浴池被判担责两成",
      "url": "https://www.baidu.com/s?wd=%E8%80%81%E4%BA%BA%E9%85%92%E5%90%8E%E6%B3%A1%E6%BE%A1%E6%AD%BB%E4%BA%A1+%E6%B5%B4%E6%B1%A0%E8%A2%AB%E5%88%A4%E6%8B%85%E8%B4%A3%E4%B8%A4%E6%88%90&sa=fyb_news&rsv_dl=fyb_news",
      "meta": "6279625"
    },
    {
      "rank": 19,
      "title": "女子被骗10万不甘心 设局反钓骗子",
      "url": "https://www.baidu.com/s?wd=%E5%A5%B3%E5%AD%90%E8%A2%AB%E9%AA%9710%E4%B8%87%E4%B8%8D%E7%94%98%E5%BF%83+%E8%AE%BE%E5%B1%80%E5%8F%8D%E9%92%93%E9%AA%97%E5%AD%90&sa=fyb_news&rsv_dl=fyb_news",
      "meta": "6192816"
    },
    {
      "rank": 20,
      "title": "“希望能帮你加个菜吃顿热乎饭”",
      "url": "https://www.baidu.com/s?wd=%E2%80%9C%E5%B8%8C%E6%9C%9B%E8%83%BD%E5%B8%AE%E4%BD%A0%E5%8A%A0%E4%B8%AA%E8%8F%9C%E5%90%83%E9%A1%BF%E7%83%AD%E4%B9%8E%E9%A5%AD%E2%80%9D&sa=fyb_news&rsv_dl=fyb_news",
      "meta": "6088193"
    }
  ]
}
