{
  "source": "baidu",
  "updatedAt": "2026-05-17T11:17:20.398Z",
  "count": 20,
  "items": [
    {
      "rank": 1,
      "title": "引领新时代中俄关系不断取得新成果",
      "url": "https://www.baidu.com/s?wd=%E5%BC%95%E9%A2%86%E6%96%B0%E6%97%B6%E4%BB%A3%E4%B8%AD%E4%BF%84%E5%85%B3%E7%B3%BB%E4%B8%8D%E6%96%AD%E5%8F%96%E5%BE%97%E6%96%B0%E6%88%90%E6%9E%9C&sa=fyb_news&rsv_dl=fyb_news",
      "meta": "7904452"
    },
    {
      "rank": 2,
      "title": "四个品牌五款产品都自称销量第一",
      "url": "https://www.baidu.com/s?wd=%E5%9B%9B%E4%B8%AA%E5%93%81%E7%89%8C%E4%BA%94%E6%AC%BE%E4%BA%A7%E5%93%81%E9%83%BD%E8%87%AA%E7%A7%B0%E9%94%80%E9%87%8F%E7%AC%AC%E4%B8%80&sa=fyb_news&rsv_dl=fyb_news",
      "meta": "7808196"
    },
    {
      "rank": 3,
      "title": "王晓东被查",
      "url": "https://www.baidu.com/s?wd=%E7%8E%8B%E6%99%93%E4%B8%9C%E8%A2%AB%E6%9F%A5&sa=fyb_news&rsv_dl=fyb_news",
      "meta": "7714316"
    },
    {
      "rank": 4,
      "title": "新一批“太空快递”签收",
      "url": "https://www.baidu.com/s?wd=%E6%96%B0%E4%B8%80%E6%89%B9%E2%80%9C%E5%A4%AA%E7%A9%BA%E5%BF%AB%E9%80%92%E2%80%9D%E7%AD%BE%E6%94%B6&sa=fyb_news&rsv_dl=fyb_news",
      "meta": "7618272"
    },
    {
      "rank": 5,
      "title": "摄影师称摆拍女孩确为盲人",
      "url": "https://www.baidu.com/s?wd=%E6%91%84%E5%BD%B1%E5%B8%88%E7%A7%B0%E6%91%86%E6%8B%8D%E5%A5%B3%E5%AD%A9%E7%A1%AE%E4%B8%BA%E7%9B%B2%E4%BA%BA&sa=fyb_news&rsv_dl=fyb_news",
      "meta": "7522267"
    },
    {
      "rank": 6,
      "title": "男子婚礼随礼随了一箱1元纸币",
      "url": "https://www.baidu.com/s?wd=%E7%94%B7%E5%AD%90%E5%A9%9A%E7%A4%BC%E9%9A%8F%E7%A4%BC%E9%9A%8F%E4%BA%86%E4%B8%80%E7%AE%B11%E5%85%83%E7%BA%B8%E5%B8%81&sa=fyb_news&rsv_dl=fyb_news",
      "meta": "7428002"
    },
    {
      "rank": 7,
      "title": "老人每月话费500元 解约需付违约金",
      "url": "https://www.baidu.com/s?wd=%E8%80%81%E4%BA%BA%E6%AF%8F%E6%9C%88%E8%AF%9D%E8%B4%B9500%E5%85%83+%E8%A7%A3%E7%BA%A6%E9%9C%80%E4%BB%98%E8%BF%9D%E7%BA%A6%E9%87%91&sa=fyb_news&rsv_dl=fyb_news",
      "meta": "7332292"
    },
    {
      "rank": 8,
      "title": "小米YU7全新颜色公布：火山灰",
      "url": "https://www.baidu.com/s?wd=%E5%B0%8F%E7%B1%B3YU7%E5%85%A8%E6%96%B0%E9%A2%9C%E8%89%B2%E5%85%AC%E5%B8%83%EF%BC%9A%E7%81%AB%E5%B1%B1%E7%81%B0&sa=fyb_news&rsv_dl=fyb_news",
      "meta": "7045057"
    },
    {
      "rank": 9,
      "title": "歌手温岚进ICU3天 经纪人：仍未脱险",
      "url": "https://www.baidu.com/s?wd=%E6%AD%8C%E6%89%8B%E6%B8%A9%E5%B2%9A%E8%BF%9BICU3%E5%A4%A9+%E7%BB%8F%E7%BA%AA%E4%BA%BA%EF%BC%9A%E4%BB%8D%E6%9C%AA%E8%84%B1%E9%99%A9&sa=fyb_news&rsv_dl=fyb_news",
      "meta": "6946704"
    },
    {
      "rank": 10,
      "title": "“雁荡山飞拉达着火”系造假引流",
      "url": "https://www.baidu.com/s?wd=%E2%80%9C%E9%9B%81%E8%8D%A1%E5%B1%B1%E9%A3%9E%E6%8B%89%E8%BE%BE%E7%9D%80%E7%81%AB%E2%80%9D%E7%B3%BB%E9%80%A0%E5%81%87%E5%BC%95%E6%B5%81&sa=fyb_news&rsv_dl=fyb_news",
      "meta": "6855957"
    },
    {
      "rank": 11,
      "title": "“豆包说你那里卖野猪”",
      "url": "https://www.baidu.com/s?wd=%E2%80%9C%E8%B1%86%E5%8C%85%E8%AF%B4%E4%BD%A0%E9%82%A3%E9%87%8C%E5%8D%96%E9%87%8E%E7%8C%AA%E2%80%9D&sa=fyb_news&rsv_dl=fyb_news",
      "meta": "6758352"
    },
    {
      "rank": 12,
      "title": "老人公交上去世 救助方被索赔逾11万",
      "url": "https://www.baidu.com/s?wd=%E8%80%81%E4%BA%BA%E5%85%AC%E4%BA%A4%E4%B8%8A%E5%8E%BB%E4%B8%96+%E6%95%91%E5%8A%A9%E6%96%B9%E8%A2%AB%E7%B4%A2%E8%B5%94%E9%80%BE11%E4%B8%87&sa=fyb_news&rsv_dl=fyb_news",
      "meta": "6656166"
    },
    {
      "rank": 13,
      "title": "暴雨后路边过山鲫鱼成群赶路",
      "url": "https://www.baidu.com/s?wd=%E6%9A%B4%E9%9B%A8%E5%90%8E%E8%B7%AF%E8%BE%B9%E8%BF%87%E5%B1%B1%E9%B2%AB%E9%B1%BC%E6%88%90%E7%BE%A4%E8%B5%B6%E8%B7%AF&sa=fyb_news&rsv_dl=fyb_news",
      "meta": "6572929"
    },
    {
      "rank": 14,
      "title": "“你的5000美金已长成5万多棵树”",
      "url": "https://www.baidu.com/s?wd=%E2%80%9C%E4%BD%A0%E7%9A%845000%E7%BE%8E%E9%87%91%E5%B7%B2%E9%95%BF%E6%88%905%E4%B8%87%E5%A4%9A%E6%A3%B5%E6%A0%91%E2%80%9D&sa=fyb_news&rsv_dl=fyb_news",
      "meta": "6463233"
    },
    {
      "rank": 15,
      "title": "游客患病退年卡 动物园清空许愿池",
      "url": "https://www.baidu.com/s?wd=%E6%B8%B8%E5%AE%A2%E6%82%A3%E7%97%85%E9%80%80%E5%B9%B4%E5%8D%A1+%E5%8A%A8%E7%89%A9%E5%9B%AD%E6%B8%85%E7%A9%BA%E8%AE%B8%E6%84%BF%E6%B1%A0&sa=fyb_news&rsv_dl=fyb_news",
      "meta": "6374729"
    },
    {
      "rank": 16,
      "title": "中美阿联合重大行动战果公布",
      "url": "https://www.baidu.com/s?wd=%E4%B8%AD%E7%BE%8E%E9%98%BF%E8%81%94%E5%90%88%E9%87%8D%E5%A4%A7%E8%A1%8C%E5%8A%A8%E6%88%98%E6%9E%9C%E5%85%AC%E5%B8%83&sa=fyb_news&rsv_dl=fyb_news",
      "meta": "6273918"
    },
    {
      "rank": 17,
      "title": "国民党副主席回应特朗普涉台表态",
      "url": "https://www.baidu.com/s?wd=%E5%9B%BD%E6%B0%91%E5%85%9A%E5%89%AF%E4%B8%BB%E5%B8%AD%E5%9B%9E%E5%BA%94%E7%89%B9%E6%9C%97%E6%99%AE%E6%B6%89%E5%8F%B0%E8%A1%A8%E6%80%81&sa=fyb_news&rsv_dl=fyb_news",
      "meta": "6178684"
    },
    {
      "rank": 18,
      "title": "《给阿嬷的情书》破4亿 导演深夜发文",
      "url": "https://www.baidu.com/s?wd=%E3%80%8A%E7%BB%99%E9%98%BF%E5%AC%B7%E7%9A%84%E6%83%85%E4%B9%A6%E3%80%8B%E7%A0%B44%E4%BA%BF+%E5%AF%BC%E6%BC%94%E6%B7%B1%E5%A4%9C%E5%8F%91%E6%96%87&sa=fyb_news&rsv_dl=fyb_news",
      "meta": "6078764"
    },
    {
      "rank": 19,
      "title": "梅花鹿被学生过度投喂撑死？物业回应",
      "url": "https://www.baidu.com/s?wd=%E6%A2%85%E8%8A%B1%E9%B9%BF%E8%A2%AB%E5%AD%A6%E7%94%9F%E8%BF%87%E5%BA%A6%E6%8A%95%E5%96%82%E6%92%91%E6%AD%BB%EF%BC%9F%E7%89%A9%E4%B8%9A%E5%9B%9E%E5%BA%94&sa=fyb_news&rsv_dl=fyb_news",
      "meta": "5998588"
    },
    {
      "rank": 20,
      "title": "FBI悬赏20万美元通缉前女特工",
      "url": "https://www.baidu.com/s?wd=FBI%E6%82%AC%E8%B5%8F20%E4%B8%87%E7%BE%8E%E5%85%83%E9%80%9A%E7%BC%89%E5%89%8D%E5%A5%B3%E7%89%B9%E5%B7%A5&sa=fyb_news&rsv_dl=fyb_news",
      "meta": "5901429"
    }
  ]
}
