{
  "source": "sina",
  "updatedAt": "2026-03-25T23:53:10.425Z",
  "count": 10,
  "items": [
    {
      "rank": 1,
      "title": "专家说黄金正重演08年剧本",
      "url": "https://s.weibo.com/weibo?q=%E4%B8%93%E5%AE%B6%E8%AF%B4%E9%BB%84%E9%87%91%E6%AD%A3%E9%87%8D%E6%BC%9408%E5%B9%B4%E5%89%A7%E6%9C%AC",
      "meta": "话题"
    },
    {
      "rank": 2,
      "title": "32岁产妇羊水栓塞成植物人",
      "url": "https://s.weibo.com/weibo?q=32%E5%B2%81%E4%BA%A7%E5%A6%87%E7%BE%8A%E6%B0%B4%E6%A0%93%E5%A1%9E%E6%88%90%E6%A4%8D%E7%89%A9%E4%BA%BA",
      "meta": "话题"
    },
    {
      "rank": 3,
      "title": "日方回应自卫队人员强闯我大使馆",
      "url": "https://s.weibo.com/weibo?q=%E6%97%A5%E6%96%B9%E5%9B%9E%E5%BA%94%E8%87%AA%E5%8D%AB%E9%98%9F%E4%BA%BA%E5%91%98%E5%BC%BA%E9%97%AF%E6%88%91%E5%A4%A7%E4%BD%BF%E9%A6%86",
      "meta": "话题"
    },
    {
      "rank": 4,
      "title": "21岁女子为养团播男友打2份工",
      "url": "https://s.weibo.com/weibo?q=21%E5%B2%81%E5%A5%B3%E5%AD%90%E4%B8%BA%E5%85%BB%E5%9B%A2%E6%92%AD%E7%94%B7%E5%8F%8B%E6%89%932%E4%BB%BD%E5%B7%A5",
      "meta": "话题"
    },
    {
      "rank": 5,
      "title": "于东来宣布每人退3000元",
      "url": "https://s.weibo.com/weibo?q=%E4%BA%8E%E4%B8%9C%E6%9D%A5%E5%AE%A3%E5%B8%83%E6%AF%8F%E4%BA%BA%E9%80%803000%E5%85%83",
      "meta": "话题"
    },
    {
      "rank": 6,
      "title": "福农优品我在家乡等你来",
      "url": "https://s.weibo.com/weibo?q=%E7%A6%8F%E5%86%9C%E4%BC%98%E5%93%81%E6%88%91%E5%9C%A8%E5%AE%B6%E4%B9%A1%E7%AD%89%E4%BD%A0%E6%9D%A5",
      "meta": "话题"
    },
    {
      "rank": 7,
      "title": "中方坚决反对美强行控制一国元首",
      "url": "https://s.weibo.com/weibo?q=%E4%B8%AD%E6%96%B9%E5%9D%9A%E5%86%B3%E5%8F%8D%E5%AF%B9%E7%BE%8E%E5%BC%BA%E8%A1%8C%E6%8E%A7%E5%88%B6%E4%B8%80%E5%9B%BD%E5%85%83%E9%A6%96",
      "meta": "话题"
    },
    {
      "rank": 8,
      "title": "“生命科学”骗局大起底！",
      "url": "https://news.sina.com.cn/gov/2026-03-25/doc-inhsecse6991675.shtml",
      "meta": "新闻"
    },
    {
      "rank": 9,
      "title": "刘晓庆接手妹妹的儿子抚养",
      "url": "https://k.sina.com.cn/article_7879776328_1d5abd84806801e4ne.html?from=ent&subch=oent",
      "meta": "新闻"
    },
    {
      "rank": 10,
      "title": "张雪峰追悼会",
      "url": "https://news.sina.cn/sh/2026-03-26/detail-inhsfrtk0717929.d.html",
      "meta": "新闻"
    }
  ]
}
