{
  "source": "sina",
  "updatedAt": "2026-07-11T10:21:02.677Z",
  "count": 8,
  "items": [
    {
      "rank": 1,
      "title": "你要知道的防汛知识点",
      "url": "https://k.sina.com.cn/article_7857201856_1d45362c00190831gs.html?from=auto&subch=oauto",
      "meta": "新闻"
    },
    {
      "rank": 2,
      "title": "巴威登陆地点有变",
      "url": "https://k.sina.com.cn/article_5952915705_162d248f906703b7ca.html?from=news",
      "meta": "新闻"
    },
    {
      "rank": 3,
      "title": "曝余承东内部群发飙",
      "url": "https://s.weibo.com/weibo?q=%E6%9B%9D%E4%BD%99%E6%89%BF%E4%B8%9C%E5%86%85%E9%83%A8%E7%BE%A4%E5%8F%91%E9%A3%99",
      "meta": "话题"
    },
    {
      "rank": 4,
      "title": "内马尔度假遭痛批",
      "url": "https://k.sina.com.cn/article_1584526667_5e71f54b040036de6.html?from=sports&subch=osport",
      "meta": "新闻"
    },
    {
      "rank": 5,
      "title": "巴威最新位置",
      "url": "https://s.weibo.com/weibo?q=%E5%B7%B4%E5%A8%81%E6%9C%80%E6%96%B0%E4%BD%8D%E7%BD%AE",
      "meta": "话题"
    },
    {
      "rank": 6,
      "title": "“灾后恢复供电要交纳高额抢修费”不实",
      "url": "https://news.sina.com.cn/o/2026-07-10/doc-inihifxw7132466.shtml",
      "meta": "新闻"
    },
    {
      "rank": 7,
      "title": "纽约前辉瑞大楼承重柱弯曲如面条",
      "url": "https://k.sina.com.cn/article_7879848931_1d5acf3e306801ar22.html?from=news&subch=onews",
      "meta": "新闻"
    },
    {
      "rank": 8,
      "title": "Jennie神图诞生了",
      "url": "https://s.weibo.com/weibo?q=Jennie%E7%A5%9E%E5%9B%BE%E8%AF%9E%E7%94%9F%E4%BA%86",
      "meta": "话题"
    }
  ]
}
