{
  "source": "sina",
  "updatedAt": "2026-07-10T21:13:32.970Z",
  "count": 20,
  "items": [
    {
      "rank": 1,
      "title": "撸起袖子加油干，移民村变身幸福村——记全国先进基层党组织岢岚县宋家沟镇宋家沟村党支部",
      "url": "https://news.sina.com.cn/zx/gj/2026-07-11/doc-inihiwvt8430313.shtml",
      "meta": "新闻"
    },
    {
      "rank": 2,
      "title": "防汛时评｜思想麻痹是比洪水更危险的“管涌”",
      "url": "https://news.sina.com.cn/zx/gj/2026-07-10/doc-inihhzsa3932947.shtml",
      "meta": "新闻"
    },
    {
      "rank": 3,
      "title": "【好评中国】以科创为炬，照亮中国式现代化征途",
      "url": "https://news.sina.com.cn/zx/gj/2026-07-10/doc-inihhzsa3920294.shtml",
      "meta": "新闻"
    },
    {
      "rank": 4,
      "title": "【好评中国】AI漫评：铁旅融合绘新卷，火车载梦赴山海",
      "url": "https://news.sina.com.cn/zx/gj/2026-07-10/doc-inihhzry7143645.shtml",
      "meta": "新闻"
    },
    {
      "rank": 5,
      "title": "知否丨暴雨季如何避险自救？急诊专家支招汛期健康防护",
      "url": "https://news.sina.com.cn/zx/gj/2026-07-10/doc-inihhzsc8444119.shtml",
      "meta": "新闻"
    },
    {
      "rank": 6,
      "title": "山海共潮生 | 一位骨科医生“连接”山海健康路",
      "url": "https://news.sina.com.cn/zx/gj/2026-07-10/doc-inihinfz5206723.shtml",
      "meta": "新闻"
    },
    {
      "rank": 7,
      "title": "内需升温 开放提速——南昌双擎驱动激活高质量发展新动能",
      "url": "https://news.sina.com.cn/zx/gj/2026-07-10/doc-inihhvke3899366.shtml",
      "meta": "新闻"
    },
    {
      "rank": 8,
      "title": "社区筑“童缘” 盛夏伴成长",
      "url": "https://news.sina.com.cn/zx/gj/2026-07-10/doc-inihftwv5282130.shtml",
      "meta": "新闻"
    },
    {
      "rank": 9,
      "title": "包头：当好东道主 以过硬实力冲击赛场荣誉",
      "url": "https://news.sina.com.cn/zx/gj/2026-07-09/doc-inihfpqv8508767.shtml",
      "meta": "新闻"
    },
    {
      "rank": 10,
      "title": "外媒说丨中国人工智能效率优势成为全球新看点",
      "url": "https://news.sina.com.cn/zx/gj/2026-07-10/doc-inihftwv5279598.shtml",
      "meta": "新闻"
    },
    {
      "rank": 11,
      "title": "云旗上身Germanier未发布款",
      "url": "https://s.weibo.com/weibo?q=%23%E4%BA%91%E6%97%97%E4%B8%8A%E8%BA%ABGermanier%E6%9C%AA%E5%8F%91%E5%B8%83%E6%AC%BE%23",
      "meta": "话题"
    },
    {
      "rank": 12,
      "title": "IU李知恩积家全球品牌大使",
      "url": "https://s.weibo.com/weibo?q=IU%E6%9D%8E%E7%9F%A5%E6%81%A9%E7%A7%AF%E5%AE%B6%E5%85%A8%E7%90%83%E5%93%81%E7%89%8C%E5%A4%A7%E4%BD%BF",
      "meta": "话题"
    },
    {
      "rank": 13,
      "title": "戴燕妮巴黎高定周",
      "url": "https://s.weibo.com/weibo?q=%E6%88%B4%E7%87%95%E5%A6%AE%E5%B7%B4%E9%BB%8E%E9%AB%98%E5%AE%9A%E5%91%A8",
      "meta": "话题"
    },
    {
      "rank": 14,
      "title": "平和从容面对八强魔咒，西班牙主帅：亚马尔高光时刻还没来",
      "url": "https://news.sina.cn/zt_d/subject-1774997568",
      "meta": "新闻"
    },
    {
      "rank": 15,
      "title": "泉州市市长：向所有遇难者家属、向全社会诚恳道歉",
      "url": "https://news.sina.com.cn/o/2026-07-10/doc-inihhvki5191206.shtml",
      "meta": "新闻"
    },
    {
      "rank": 16,
      "title": "福建泉州晋江一鞋厂发生火灾 现场有人员被困",
      "url": "https://news.sina.com.cn/c/2026-07-09/doc-inihewta4418187.shtml",
      "meta": "新闻"
    },
    {
      "rank": 17,
      "title": "“坟爷”林耀昌聚众斗殴罪案被害人申请检方抗诉被驳",
      "url": "https://news.sina.com.cn/s/2026-07-09/doc-inihewsy7616640.shtml",
      "meta": "新闻"
    },
    {
      "rank": 18,
      "title": "网传几分钱一斤？揭秘河南西瓜价差真相",
      "url": "https://news.sina.com.cn/s/2026-07-09/doc-inihenca8213234.shtml",
      "meta": "新闻"
    },
    {
      "rank": 19,
      "title": "世界杯出局后首次更新，C罗社媒发文：葡萄牙永恒",
      "url": "https://news.sina.com.cn/s/2026-07-09/doc-inihczpn4547921.shtml",
      "meta": "新闻"
    },
    {
      "rank": 20,
      "title": "15年间结婚8次，36岁女子被判刑",
      "url": "https://news.sina.com.cn/s/2026-07-08/doc-inihattw8311493.shtml",
      "meta": "新闻"
    }
  ]
}
