{
  "source": "sina",
  "updatedAt": "2026-05-24T08:41:11.548Z",
  "count": 6,
  "items": [
    {
      "rank": 1,
      "title": "长鑫科技",
      "url": "https://k.sina.com.cn/article_7857201856_1d45362c001905vm76.html?from=finance",
      "meta": "新闻"
    },
    {
      "rank": 2,
      "title": "男子踩中蛇窝被咬10多口",
      "url": "https://k.sina.com.cn/article_7857201856_1d45362c001905va6w.html?from=health",
      "meta": "新闻"
    },
    {
      "rank": 3,
      "title": "国产600公斤推力级涡扇发动机首飞成功",
      "url": "https://k.sina.com.cn/article_1496814565_593793e50200218tg.html?from=news&subch=onews",
      "meta": "新闻"
    },
    {
      "rank": 4,
      "title": "两个淡人生了个浓人宝宝",
      "url": "https://s.weibo.com/weibo?q=%E4%B8%A4%E4%B8%AA%E6%B7%A1%E4%BA%BA%E7%94%9F%E4%BA%86%E4%B8%AA%E6%B5%93%E4%BA%BA%E5%AE%9D%E5%AE%9D",
      "meta": "话题"
    },
    {
      "rank": 5,
      "title": "“西瓜谣言”不能年年辟谣年年传",
      "url": "https://k.sina.com.cn/article_1644114654_61ff32de019025dse.html?from=news&subch=onews",
      "meta": "新闻"
    },
    {
      "rank": 6,
      "title": "只要站起来会发现水其实很浅",
      "url": "https://s.weibo.com/weibo?q=%E5%8F%AA%E8%A6%81%E7%AB%99%E8%B5%B7%E6%9D%A5%E4%BC%9A%E5%8F%91%E7%8E%B0%E6%B0%B4%E5%85%B6%E5%AE%9E%E5%BE%88%E6%B5%85",
      "meta": "话题"
    }
  ]
}
