{
  "source": "sina",
  "updatedAt": "2026-04-16T03:37:43.851Z",
  "count": 5,
  "items": [
    {
      "rank": 1,
      "title": "皇马两大球星场上吵架",
      "url": "https://k.sina.com.cn/article_7857201856_1d45362c001904dm02.html?from=sports&subch=osport",
      "meta": "新闻"
    },
    {
      "rank": 2,
      "title": "樊振东英文告别主场球迷",
      "url": "https://k.sina.com.cn/article_7857201856_1d45362c001904dlas.html?from=sports&subch=osport",
      "meta": "新闻"
    },
    {
      "rank": 3,
      "title": "全国工程建设小阳春",
      "url": "https://s.weibo.com/weibo?q=%E5%85%A8%E5%9B%BD%E5%B7%A5%E7%A8%8B%E5%BB%BA%E8%AE%BE%E5%B0%8F%E9%98%B3%E6%98%A5",
      "meta": "话题"
    },
    {
      "rank": 4,
      "title": "法国将不义之财归还被抢掠的中国",
      "url": "https://k.sina.com.cn/article_1746067030_6812de56019016asw.html?from=news&subch=onews",
      "meta": "新闻"
    },
    {
      "rank": 5,
      "title": "小米史上最大电池手机曝光",
      "url": "https://k.sina.com.cn/article_7857201856_1d45362c001904dpeu.html?from=digit",
      "meta": "新闻"
    }
  ]
}
