{
  "source": "sina",
  "updatedAt": "2026-06-26T15:28:17.316Z",
  "count": 7,
  "items": [
    {
      "rank": 1,
      "title": "杨紫白玉兰视后",
      "url": "https://k.sina.com.cn/article_2770914283_a528cbeb04001nxry.html?from=ent&subch=oent",
      "meta": "新闻"
    },
    {
      "rank": 2,
      "title": "625亿元国补资金已经下达",
      "url": "https://k.sina.com.cn/article_5953189932_162d6782c06704iwym.html?from=tech",
      "meta": "新闻"
    },
    {
      "rank": 3,
      "title": "iPhone17以旧换新增超3倍",
      "url": "https://s.weibo.com/weibo?q=iPhone17%E4%BB%A5%E6%97%A7%E6%8D%A2%E6%96%B0%E5%A2%9E%E8%B6%853%E5%80%8D",
      "meta": "话题"
    },
    {
      "rank": 4,
      "title": "折叠小V单是在挑战谁",
      "url": "https://s.weibo.com/weibo?q=%E6%8A%98%E5%8F%A0%E5%B0%8FV%E5%8D%95%E6%98%AF%E5%9C%A8%E6%8C%91%E6%88%98%E8%B0%81",
      "meta": "话题"
    },
    {
      "rank": 5,
      "title": "成都温江一地起火系餐馆炼油所致 当地辟谣",
      "url": "https://k.sina.com.cn/article_1714800385_m6635c701033019jfo.html?from=news&subch=onews",
      "meta": "新闻"
    },
    {
      "rank": 6,
      "title": "肖战又拔水了",
      "url": "https://s.weibo.com/weibo?q=%E8%82%96%E6%88%98%E5%8F%88%E6%8B%94%E6%B0%B4%E4%BA%86",
      "meta": "话题"
    },
    {
      "rank": 7,
      "title": "奥斯卡欠C罗一座小金人",
      "url": "https://s.weibo.com/weibo?q=%E5%A5%A5%E6%96%AF%E5%8D%A1%E6%AC%A0C%E7%BD%97%E4%B8%80%E5%BA%A7%E5%B0%8F%E9%87%91%E4%BA%BA",
      "meta": "话题"
    }
  ]
}
