{
  "source": "sina",
  "updatedAt": "2026-03-22T13:56:55.258Z",
  "count": 9,
  "items": [
    {
      "rank": 1,
      "title": "爱吃荔枝的人今年天塌了",
      "url": "https://s.weibo.com/weibo?q=%E7%88%B1%E5%90%83%E8%8D%94%E6%9E%9D%E7%9A%84%E4%BA%BA%E4%BB%8A%E5%B9%B4%E5%A4%A9%E5%A1%8C%E4%BA%86",
      "meta": "话题"
    },
    {
      "rank": 2,
      "title": "双汇王中王火腿肠被曝吃出两根钢钉",
      "url": "https://s.weibo.com/weibo?q=%E5%8F%8C%E6%B1%87%E7%8E%8B%E4%B8%AD%E7%8E%8B%E7%81%AB%E8%85%BF%E8%82%A0%E8%A2%AB%E6%9B%9D%E5%90%83%E5%87%BA%E4%B8%A4%E6%A0%B9%E9%92%A2%E9%92%89",
      "meta": "话题"
    },
    {
      "rank": 3,
      "title": "9组数据见证大国治水生动画卷",
      "url": "https://k.sina.com.cn/article_3757167087_dff1d1ef02001er9y.html?from=news&subch=onews",
      "meta": "新闻"
    },
    {
      "rank": 4,
      "title": "我国杂交稻又有新突破了",
      "url": "https://k.sina.com.cn/article_7857201856_1d45362c001903hdr2.html?from=science",
      "meta": "新闻"
    },
    {
      "rank": 5,
      "title": "金价上演断崖式下跌",
      "url": "https://s.weibo.com/weibo?q=%E9%87%91%E4%BB%B7%E4%B8%8A%E6%BC%94%E6%96%AD%E5%B4%96%E5%BC%8F%E4%B8%8B%E8%B7%8C",
      "meta": "话题"
    },
    {
      "rank": 6,
      "title": "皇帝想娶樊长玉",
      "url": "https://s.weibo.com/weibo?q=%E7%9A%87%E5%B8%9D%E6%83%B3%E5%A8%B6%E6%A8%8A%E9%95%BF%E7%8E%89",
      "meta": "话题"
    },
    {
      "rank": 7,
      "title": "珲春一国道现巨鸟过马路",
      "url": "https://k.sina.com.cn/article_7857201856_1d45362c001903hbfs.html?from=news&subch=onews",
      "meta": "新闻"
    },
    {
      "rank": 8,
      "title": "警方辟谣“梅姨”落网地点",
      "url": "https://news.sina.cn/gn/2026-03-22/detail-inhrvnnv6408548.d.html",
      "meta": "新闻"
    },
    {
      "rank": 9,
      "title": "逐玉学一下想见你是怎么挽救的",
      "url": "https://s.weibo.com/weibo?q=%E9%80%90%E7%8E%89%E5%AD%A6%E4%B8%80%E4%B8%8B%E6%83%B3%E8%A7%81%E4%BD%A0%E6%98%AF%E6%80%8E%E4%B9%88%E6%8C%BD%E6%95%91%E7%9A%84",
      "meta": "话题"
    }
  ]
}
