{
  "source": "sina",
  "updatedAt": "2026-05-26T16:49:11.195Z",
  "count": 20,
  "items": [
    {
      "rank": 1,
      "title": "从“看天”到“看屏”：云南茶咖产业共谱数智新篇",
      "url": "https://news.sina.com.cn/zx/gj/2026-05-26/doc-inhzffsk2883307.shtml",
      "meta": "新闻"
    },
    {
      "rank": 2,
      "title": "靖江街头生死救援火爆全网，四川广安回礼：泰州市民旅游免票",
      "url": "https://news.sina.com.cn/zx/gj/2026-05-26/doc-inhzfshn1416020.shtml",
      "meta": "新闻"
    },
    {
      "rank": 3,
      "title": "老有福｜在福州养老，老人处处有“医”靠！",
      "url": "https://news.sina.com.cn/zx/gj/2026-05-26/doc-inhzfshn1372286.shtml",
      "meta": "新闻"
    },
    {
      "rank": 4,
      "title": "一湖碧水映太行",
      "url": "https://news.sina.com.cn/zx/gj/2026-05-26/doc-inhzevaq2988136.shtml",
      "meta": "新闻"
    },
    {
      "rank": 5,
      "title": "影像力 | 内蒙古文博精品精彩绽放“中国文化产业第一展”",
      "url": "https://news.sina.com.cn/zx/gj/2026-05-26/doc-inhzezkn2938843.shtml",
      "meta": "新闻"
    },
    {
      "rank": 6,
      "title": "高标准高质量建设自由贸易试验区丨陆空联动 通达欧亚 呼和浩特重塑向北开放黄金通道",
      "url": "https://news.sina.com.cn/zx/gj/2026-05-26/doc-inhzevat2403999.shtml",
      "meta": "新闻"
    },
    {
      "rank": 7,
      "title": "强降雨致校园被淹 石门县所街乡干群齐心清淤保复学",
      "url": "https://news.sina.com.cn/zx/gj/2026-05-26/doc-inhzffss1523796.shtml",
      "meta": "新闻"
    },
    {
      "rank": 8,
      "title": "梁带村芮国遗址博物馆 黄河边挖出一个神秘古国",
      "url": "https://news.sina.com.cn/zx/gj/2026-05-26/doc-inhzffsk2885460.shtml",
      "meta": "新闻"
    },
    {
      "rank": 9,
      "title": "荔刻说 | 我们评判基层干部的标尺，到底应该落在哪里？",
      "url": "https://news.sina.com.cn/zx/gj/2026-05-26/doc-inhzezks9130748.shtml",
      "meta": "新闻"
    },
    {
      "rank": 10,
      "title": "彩练漫评 | 何为“东北超”？——从赛场两个名场面读懂赛事背后的东北力量",
      "url": "https://news.sina.com.cn/zx/gj/2026-05-26/doc-inhzequs3034908.shtml",
      "meta": "新闻"
    },
    {
      "rank": 11,
      "title": "肖战提名白玉兰奖最佳男主",
      "url": "https://s.weibo.com/weibo?q=%23%E8%82%96%E6%88%98%E6%8F%90%E5%90%8D%E7%99%BD%E7%8E%89%E5%85%B0%E5%A5%96%E6%9C%80%E4%BD%B3%E7%94%B7%E4%B8%BB%23",
      "meta": "话题"
    },
    {
      "rank": 12,
      "title": "本届白玉兰意难平",
      "url": "https://s.weibo.com/weibo?q=%E6%9C%AC%E5%B1%8A%E7%99%BD%E7%8E%89%E5%85%B0%E6%84%8F%E9%9A%BE%E5%B9%B3",
      "meta": "话题"
    },
    {
      "rank": 13,
      "title": "陈鹤一红色丝带",
      "url": "https://s.weibo.com/weibo?q=%E9%99%88%E9%B9%A4%E4%B8%80%E7%BA%A2%E8%89%B2%E4%B8%9D%E5%B8%A6",
      "meta": "话题"
    },
    {
      "rank": 14,
      "title": "李昀锐白衬衫学长",
      "url": "https://s.weibo.com/weibo?q=%E6%9D%8E%E6%98%80%E9%94%90%E7%99%BD%E8%A1%AC%E8%A1%AB%E5%AD%A6%E9%95%BF",
      "meta": "话题"
    },
    {
      "rank": 15,
      "title": "穿阔腿裤最害怕遇到的事",
      "url": "https://s.weibo.com/weibo?q=%E7%A9%BF%E9%98%94%E8%85%BF%E8%A3%A4%E6%9C%80%E5%AE%B3%E6%80%95%E9%81%87%E5%88%B0%E7%9A%84%E4%BA%8B",
      "meta": "话题"
    },
    {
      "rank": 16,
      "title": "Jennie香奈儿首尔大秀",
      "url": "https://s.weibo.com/weibo?q=Jennie%E9%A6%99%E5%A5%88%E5%84%BF%E9%A6%96%E5%B0%94%E5%A4%A7%E7%A7%80",
      "meta": "话题"
    },
    {
      "rank": 17,
      "title": "Jennie红唇大波浪",
      "url": "https://s.weibo.com/weibo?q=Jennie%E7%BA%A2%E5%94%87%E5%A4%A7%E6%B3%A2%E6%B5%AA",
      "meta": "话题"
    },
    {
      "rank": 18,
      "title": "王玉雯春游摆小摊OOTD",
      "url": "https://s.weibo.com/weibo?q=%E7%8E%8B%E7%8E%89%E9%9B%AF%E6%98%A5%E6%B8%B8%E6%91%86%E5%B0%8F%E6%91%8AOOTD",
      "meta": "话题"
    },
    {
      "rank": 19,
      "title": "纪梵希油条3元一根",
      "url": "https://s.weibo.com/weibo?q=%23%E7%BA%AA%E6%A2%B5%E5%B8%8C%E6%B2%B9%E6%9D%A13%E5%85%83%E4%B8%80%E6%A0%B9%23",
      "meta": "话题"
    },
    {
      "rank": 20,
      "title": "郝熠然牛仔风ootd",
      "url": "https://s.weibo.com/weibo?q=%E9%83%9D%E7%86%A0%E7%84%B6%E7%89%9B%E4%BB%94%E9%A3%8Eootd",
      "meta": "话题"
    }
  ]
}
