{
  "source": "sina",
  "updatedAt": "2026-05-30T22:06:26.192Z",
  "count": 20,
  "items": [
    {
      "rank": 1,
      "title": "鸭绿江畔的“兴边合伙人”",
      "url": "https://news.sina.com.cn/zx/gj/2026-05-31/doc-inhztipy6725291.shtml",
      "meta": "新闻"
    },
    {
      "rank": 2,
      "title": "海上粮仓喜获丰收！国产高品质三文鱼集中起捕上市",
      "url": "https://news.sina.com.cn/zx/gj/2026-05-30/doc-inhzsssm6795312.shtml",
      "meta": "新闻"
    },
    {
      "rank": 3,
      "title": "麦收时节丨雨后抢收的新农人",
      "url": "https://news.sina.com.cn/zx/gj/2026-05-30/doc-inhzsssm6791007.shtml",
      "meta": "新闻"
    },
    {
      "rank": 4,
      "title": "河南：麦浪翻滚机声隆 抢收抢烘保丰收",
      "url": "https://news.sina.com.cn/zx/gj/2026-05-30/doc-inhzrzup8809789.shtml",
      "meta": "新闻"
    },
    {
      "rank": 5,
      "title": "包头市新增500个夜间潮汐车位 错峰共享破解停车难",
      "url": "https://news.sina.com.cn/zx/gj/2026-05-30/doc-inhzreqy7581461.shtml",
      "meta": "新闻"
    },
    {
      "rank": 6,
      "title": "北京力争通过五年努力，经济高质量发展迈上新台阶",
      "url": "https://news.sina.com.cn/zx/gj/2026-05-30/doc-inhzrzup8809978.shtml",
      "meta": "新闻"
    },
    {
      "rank": 7,
      "title": "兰州：和善少年逐艺梦 乐动童年绽芳华",
      "url": "https://news.sina.com.cn/zx/gj/2026-05-30/doc-inhzrzup8809808.shtml",
      "meta": "新闻"
    },
    {
      "rank": 8,
      "title": "绿满陇原·奇迹三北 | 敦煌筑牢三道绿屏 绘就丝路绿进沙退新画卷",
      "url": "https://news.sina.com.cn/zx/gj/2026-05-30/doc-inhzshar6961983.shtml",
      "meta": "新闻"
    },
    {
      "rank": 9,
      "title": "花园里的北京｜朝阳公园的市集里，我们吃到了“彩虹”西瓜",
      "url": "https://news.sina.com.cn/zx/gj/2026-05-30/doc-inhzrzut7049060.shtml",
      "meta": "新闻"
    },
    {
      "rank": 10,
      "title": "安徽省6家企业入选工信部2025年5G工厂典型应用实践 全国第五",
      "url": "https://news.sina.com.cn/zx/gj/2026-05-29/doc-inhzqccn7933791.shtml",
      "meta": "新闻"
    },
    {
      "rank": 11,
      "title": "田栩宁什么帽子你的美貌",
      "url": "https://s.weibo.com/weibo?q=%E7%94%B0%E6%A0%A9%E5%AE%81%E4%BB%80%E4%B9%88%E5%B8%BD%E5%AD%90%E4%BD%A0%E7%9A%84%E7%BE%8E%E8%B2%8C",
      "meta": "话题"
    },
    {
      "rank": 12,
      "title": "杨紫四度入围白玉兰奖",
      "url": "https://s.weibo.com/weibo?q=%E6%9D%A8%E7%B4%AB%E5%9B%9B%E5%BA%A6%E5%85%A5%E5%9B%B4%E7%99%BD%E7%8E%89%E5%85%B0%E5%A5%96",
      "meta": "话题"
    },
    {
      "rank": 13,
      "title": "肖战机场无袖穿搭",
      "url": "https://s.weibo.com/weibo?q=%E8%82%96%E6%88%98%E6%9C%BA%E5%9C%BA%E6%97%A0%E8%A2%96%E7%A9%BF%E6%90%AD",
      "meta": "话题"
    },
    {
      "rank": 14,
      "title": "LV太子妃怀孕",
      "url": "https://s.weibo.com/weibo?q=%23LV%E5%A4%AA%E5%AD%90%E5%A6%83%E6%80%80%E5%AD%95%23",
      "meta": "话题"
    },
    {
      "rank": 15,
      "title": "姜乘澜亚裔混血感妆容",
      "url": "https://s.weibo.com/weibo?q=%E5%A7%9C%E4%B9%98%E6%BE%9C%E4%BA%9A%E8%A3%94%E6%B7%B7%E8%A1%80%E6%84%9F%E5%A6%86%E5%AE%B9",
      "meta": "话题"
    },
    {
      "rank": 16,
      "title": "上海警方：某高校在读学生沈某（男，32岁）被拘留",
      "url": "https://news.sina.com.cn/s/2026-05-29/doc-inhzqimi9455340.shtml",
      "meta": "新闻"
    },
    {
      "rank": 17,
      "title": "官方通报幼儿园教师烫伤学生：涉事教师被停职",
      "url": "https://news.sina.com.cn/s/2026-05-29/doc-inhzqccq0910958.shtml",
      "meta": "新闻"
    },
    {
      "rank": 18,
      "title": "“浪姐”宿舍甲醛超标致多人不适？节目组回应",
      "url": "https://news.sina.com.cn/s/2026-05-28/doc-inhznenk8514036.shtml",
      "meta": "新闻"
    },
    {
      "rank": 19,
      "title": "记者暗访遭拖拽致骨折，中国记协发声",
      "url": "https://news.sina.com.cn/s/2026-05-28/doc-inhzmpqp1158646.shtml",
      "meta": "新闻"
    },
    {
      "rank": 20,
      "title": "中国情侣以富士山为背景跳舞，遭日本网民网暴",
      "url": "https://news.sina.com.cn/s/2026-05-28/doc-inhzmihu0254942.shtml",
      "meta": "新闻"
    }
  ]
}
