{
  "source": "sina",
  "updatedAt": "2026-03-09T05:14:18.014Z",
  "count": 6,
  "items": [
    {
      "rank": 1,
      "title": "最高法最高检工作报告",
      "url": "https://k.sina.com.cn/article_7857201856_1d45362c001902zzcm.html?from=news&subch=onews",
      "meta": "新闻"
    },
    {
      "rank": 2,
      "title": "从基层一线走进人民殿堂",
      "url": "https://s.weibo.com/weibo?q=%E4%BB%8E%E5%9F%BA%E5%B1%82%E4%B8%80%E7%BA%BF%E8%B5%B0%E8%BF%9B%E4%BA%BA%E6%B0%91%E6%AE%BF%E5%A0%82",
      "meta": "话题"
    },
    {
      "rank": 3,
      "title": "建议处罚加班严重企业",
      "url": "https://s.weibo.com/weibo?q=%E5%BB%BA%E8%AE%AE%E5%A4%84%E7%BD%9A%E5%8A%A0%E7%8F%AD%E4%B8%A5%E9%87%8D%E4%BC%81%E4%B8%9A",
      "meta": "话题"
    },
    {
      "rank": 4,
      "title": "员工因业绩不达标被罚跪？假的",
      "url": "https://k.sina.com.cn/article_1887344341_707e96d502001qdsy.html?from=news&subch=onews",
      "meta": "新闻"
    },
    {
      "rank": 5,
      "title": "逐玉因平台缺爆款被迫爆",
      "url": "https://s.weibo.com/weibo?q=%E9%80%90%E7%8E%89%E5%9B%A0%E5%B9%B3%E5%8F%B0%E7%BC%BA%E7%88%86%E6%AC%BE%E8%A2%AB%E8%BF%AB%E7%88%86",
      "meta": "话题"
    },
    {
      "rank": 6,
      "title": "哈梅内伊之子接任最高领袖",
      "url": "https://s.weibo.com/weibo?q=%E5%93%88%E6%A2%85%E5%86%85%E4%BC%8A%E4%B9%8B%E5%AD%90%E6%8E%A5%E4%BB%BB%E6%9C%80%E9%AB%98%E9%A2%86%E8%A2%96",
      "meta": "话题"
    }
  ]
}
