{
  "source": "zibo",
  "updatedAt": "2026-05-17T22:59:38.481Z",
  "count": 4,
  "items": [
    {
      "rank": 1,
      "title": "健康活力跑",
      "url": "http://www.zbnews.net/content/2026-05/17/content_3192789.html",
      "meta": "zbnews.net"
    },
    {
      "rank": 2,
      "title": "赶订单 生产忙",
      "url": "http://www.zbnews.net/content/2026-05/15/content_3192646.html",
      "meta": "zbnews.net"
    },
    {
      "rank": 3,
      "title": "交管机器人在杭州街头“上岗”",
      "url": "http://www.zbnews.net/content/2026-05/13/content_3192526.html",
      "meta": "zbnews.net"
    },
    {
      "rank": 4,
      "title": "“善小”科普进校园",
      "url": "http://www.zbnews.net/content/2026-05/12/content_3192450.html",
      "meta": "zbnews.net"
    }
  ],
  "sections": [
    {
      "key": "local",
      "title": "淄博新闻网",
      "items": [
        {
          "rank": 1,
          "title": "健康活力跑",
          "url": "http://www.zbnews.net/content/2026-05/17/content_3192789.html",
          "meta": "zbnews.net"
        },
        {
          "rank": 2,
          "title": "赶订单 生产忙",
          "url": "http://www.zbnews.net/content/2026-05/15/content_3192646.html",
          "meta": "zbnews.net"
        },
        {
          "rank": 3,
          "title": "交管机器人在杭州街头“上岗”",
          "url": "http://www.zbnews.net/content/2026-05/13/content_3192526.html",
          "meta": "zbnews.net"
        },
        {
          "rank": 4,
          "title": "“善小”科普进校园",
          "url": "http://www.zbnews.net/content/2026-05/12/content_3192450.html",
          "meta": "zbnews.net"
        }
      ]
    },
    {
      "key": "province",
      "title": "省级媒体里的淄博",
      "items": []
    }
  ]
}
