{
  "source": "zibo",
  "updatedAt": "2026-03-20T11:58:14.676Z",
  "count": 14,
  "items": [
    {
      "rank": 1,
      "title": "首个“国际太极拳日”举行",
      "url": "http://www.zbnews.net/content/2026-03/19/content_3189163.html",
      "meta": "zbnews.net"
    },
    {
      "rank": 2,
      "title": "包饺子 待客来",
      "url": "http://www.zbnews.net/content/2026-03/18/content_3189103.html",
      "meta": "zbnews.net"
    },
    {
      "rank": 3,
      "title": "杏花绽放 引客来",
      "url": "http://www.zbnews.net/content/2026-03/18/content_3189034.html",
      "meta": "zbnews.net"
    },
    {
      "rank": 4,
      "title": "第二艘国产大型邮轮计划3月20日出坞",
      "url": "http://www.zbnews.net/content/2026-03/17/content_3188960.html",
      "meta": "zbnews.net"
    },
    {
      "rank": 5,
      "title": "庆章高速高青段建设按下“加速键”",
      "url": "http://www.zbnews.net/content/2026-03/16/content_3188899.html",
      "meta": "zbnews.net"
    },
    {
      "rank": 1,
      "title": "淄博市_ 精神卫生中心:党建引领护健康 惠民实事暖民心",
      "url": "https://baijiahao.baidu.com/s?id=1860166030022013134&wfr=spider&for=pc",
      "meta": "baijiahao.baidu.com"
    },
    {
      "rank": 2,
      "title": "山东 _淄博_ 春风送岗精准服务促就业",
      "url": "https://baijiahao.baidu.com/s?id=1860147878243990180&wfr=spider&for=pc",
      "meta": "baijiahao.baidu.com"
    },
    {
      "rank": 3,
      "title": "淄博市_ 公开征集社区养老服务提升建议",
      "url": "http://news.10jqka.com.cn/20260320/c675426387.shtml",
      "meta": "news.10jqka.com.cn"
    },
    {
      "rank": 4,
      "title": "淄博市_ 博山区中心路小学学雷锋爱心义卖活动圆满开展",
      "url": "https://baijiahao.baidu.com/s?id=1860145016906685328&wfr=spider&for=pc",
      "meta": "baijiahao.baidu.com"
    },
    {
      "rank": 5,
      "title": "淄博_ 师专附属学校召开体质健康提升工作推进会",
      "url": "https://baijiahao.baidu.com/s?id=1860159960635289527&wfr=spider&for=pc",
      "meta": "baijiahao.baidu.com"
    },
    {
      "rank": 6,
      "title": "感知齐鲁文化 体验匠技传承 _淄博_ 职业技术大学开展传统文化体验活动",
      "url": "https://baijiahao.baidu.com/s?id=1860167130854855170&wfr=spider&for=pc",
      "meta": "baijiahao.baidu.com"
    },
    {
      "rank": 7,
      "title": "用心服务暖旅途 文明窗口树形象 山东高速 _淄博_ 运管中心博兴...",
      "url": "https://baijiahao.baidu.com/s?id=1860169459703112600&wfr=spider&for=pc",
      "meta": "baijiahao.baidu.com"
    },
    {
      "rank": 8,
      "title": "淄博_ 两大创业园区推出多重福利扶持创业者",
      "url": "http://news.10jqka.com.cn/20260320/c675433103.shtml",
      "meta": "news.10jqka.com.cn"
    },
    {
      "rank": 9,
      "title": "齐韵书香·馆校共读 _淄博市_ 中小学必读书目名师讲堂首期即将开讲",
      "url": "https://baijiahao.baidu.com/s?id=1860152033020836834&wfr=spider&for=pc",
      "meta": "baijiahao.baidu.com"
    }
  ],
  "sections": [
    {
      "key": "local",
      "title": "淄博新闻网",
      "items": [
        {
          "rank": 1,
          "title": "首个“国际太极拳日”举行",
          "url": "http://www.zbnews.net/content/2026-03/19/content_3189163.html",
          "meta": "zbnews.net"
        },
        {
          "rank": 2,
          "title": "包饺子 待客来",
          "url": "http://www.zbnews.net/content/2026-03/18/content_3189103.html",
          "meta": "zbnews.net"
        },
        {
          "rank": 3,
          "title": "杏花绽放 引客来",
          "url": "http://www.zbnews.net/content/2026-03/18/content_3189034.html",
          "meta": "zbnews.net"
        },
        {
          "rank": 4,
          "title": "第二艘国产大型邮轮计划3月20日出坞",
          "url": "http://www.zbnews.net/content/2026-03/17/content_3188960.html",
          "meta": "zbnews.net"
        },
        {
          "rank": 5,
          "title": "庆章高速高青段建设按下“加速键”",
          "url": "http://www.zbnews.net/content/2026-03/16/content_3188899.html",
          "meta": "zbnews.net"
        }
      ]
    },
    {
      "key": "province",
      "title": "省级媒体里的淄博",
      "items": [
        {
          "rank": 1,
          "title": "淄博市_ 精神卫生中心:党建引领护健康 惠民实事暖民心",
          "url": "https://baijiahao.baidu.com/s?id=1860166030022013134&wfr=spider&for=pc",
          "meta": "baijiahao.baidu.com"
        },
        {
          "rank": 2,
          "title": "山东 _淄博_ 春风送岗精准服务促就业",
          "url": "https://baijiahao.baidu.com/s?id=1860147878243990180&wfr=spider&for=pc",
          "meta": "baijiahao.baidu.com"
        },
        {
          "rank": 3,
          "title": "淄博市_ 公开征集社区养老服务提升建议",
          "url": "http://news.10jqka.com.cn/20260320/c675426387.shtml",
          "meta": "news.10jqka.com.cn"
        },
        {
          "rank": 4,
          "title": "淄博市_ 博山区中心路小学学雷锋爱心义卖活动圆满开展",
          "url": "https://baijiahao.baidu.com/s?id=1860145016906685328&wfr=spider&for=pc",
          "meta": "baijiahao.baidu.com"
        },
        {
          "rank": 5,
          "title": "淄博_ 师专附属学校召开体质健康提升工作推进会",
          "url": "https://baijiahao.baidu.com/s?id=1860159960635289527&wfr=spider&for=pc",
          "meta": "baijiahao.baidu.com"
        },
        {
          "rank": 6,
          "title": "感知齐鲁文化 体验匠技传承 _淄博_ 职业技术大学开展传统文化体验活动",
          "url": "https://baijiahao.baidu.com/s?id=1860167130854855170&wfr=spider&for=pc",
          "meta": "baijiahao.baidu.com"
        },
        {
          "rank": 7,
          "title": "用心服务暖旅途 文明窗口树形象 山东高速 _淄博_ 运管中心博兴...",
          "url": "https://baijiahao.baidu.com/s?id=1860169459703112600&wfr=spider&for=pc",
          "meta": "baijiahao.baidu.com"
        },
        {
          "rank": 8,
          "title": "淄博_ 两大创业园区推出多重福利扶持创业者",
          "url": "http://news.10jqka.com.cn/20260320/c675433103.shtml",
          "meta": "news.10jqka.com.cn"
        },
        {
          "rank": 9,
          "title": "齐韵书香·馆校共读 _淄博市_ 中小学必读书目名师讲堂首期即将开讲",
          "url": "https://baijiahao.baidu.com/s?id=1860152033020836834&wfr=spider&for=pc",
          "meta": "baijiahao.baidu.com"
        }
      ]
    }
  ]
}
