{
  "source": "zibo",
  "updatedAt": "2026-04-29T04:33:40.299Z",
  "count": 13,
  "items": [
    {
      "rank": 1,
      "title": "关爱新业态 普法护健康",
      "url": "http://www.zbnews.net/content/2026-04/28/content_3191700.html",
      "meta": "zbnews.net"
    },
    {
      "rank": 2,
      "title": "引用新技术 激发新动能",
      "url": "http://www.zbnews.net/content/2026-04/28/content_3191633.html",
      "meta": "zbnews.net"
    },
    {
      "rank": 3,
      "title": "冲向山巅",
      "url": "http://www.zbnews.net/content/2026-04/27/content_3191574.html",
      "meta": "zbnews.net"
    },
    {
      "rank": 4,
      "title": "检修改造保供电",
      "url": "http://www.zbnews.net/content/2026-04/26/content_3191519.html",
      "meta": "zbnews.net"
    },
    {
      "rank": 5,
      "title": "茶树管护忙",
      "url": "http://www.zbnews.net/content/2026-04/24/content_3191378.html",
      "meta": "zbnews.net"
    },
    {
      "rank": 1,
      "title": "好客山东燃情 _淄博_ 厚植融合发展优势",
      "url": "https://baijiahao.baidu.com/s?id=1863770562488909836&wfr=spider&for=pc",
      "meta": "baijiahao.baidu.com"
    },
    {
      "rank": 2,
      "title": "五一假期临近 _淄博_ 博山交警送教进课堂",
      "url": "https://baijiahao.baidu.com/s?id=1863775915719535020&wfr=spider&for=pc",
      "meta": "baijiahao.baidu.com"
    },
    {
      "rank": 3,
      "title": "淄博_ 9人(集体)荣获全国五一劳动奖表彰",
      "url": "http://news.10jqka.com.cn/20260429/c676363720.shtml",
      "meta": "news.10jqka.com.cn"
    },
    {
      "rank": 4,
      "title": "淄博_ 傅山地质博物馆人气爆棚,亲子研学热掀起科普新风尚",
      "url": "https://baijiahao.baidu.com/s?id=1863762572627204747&wfr=spider&for=pc",
      "meta": "baijiahao.baidu.com"
    },
    {
      "rank": 5,
      "title": "淄博_ 海关联合科技局举办政策宣讲会 助力科创企业降本增效",
      "url": "http://news.10jqka.com.cn/20260429/c676363692.shtml",
      "meta": "news.10jqka.com.cn"
    },
    {
      "rank": 6,
      "title": "属于 _淄博_ 的浪漫!城市书房藏烟火,一缕书香润全城",
      "url": "https://baijiahao.baidu.com/s?id=1863766251190361646&wfr=spider&for=pc",
      "meta": "baijiahao.baidu.com"
    },
    {
      "rank": 7,
      "title": "五一暖心护航丨山东移动 _淄博_ 分公司赋能城市奋斗者",
      "url": "https://baijiahao.baidu.com/s?id=1863773300032895706&wfr=spider&for=pc",
      "meta": "baijiahao.baidu.com"
    },
    {
      "rank": 8,
      "title": "以赛育才 _淄博_ 陶琉匠人同台竞技激活产业新动能",
      "url": "https://baijiahao.baidu.com/s?id=1863718730429299740&wfr=spider&for=pc",
      "meta": "baijiahao.baidu.com"
    }
  ],
  "sections": [
    {
      "key": "local",
      "title": "淄博新闻网",
      "items": [
        {
          "rank": 1,
          "title": "关爱新业态 普法护健康",
          "url": "http://www.zbnews.net/content/2026-04/28/content_3191700.html",
          "meta": "zbnews.net"
        },
        {
          "rank": 2,
          "title": "引用新技术 激发新动能",
          "url": "http://www.zbnews.net/content/2026-04/28/content_3191633.html",
          "meta": "zbnews.net"
        },
        {
          "rank": 3,
          "title": "冲向山巅",
          "url": "http://www.zbnews.net/content/2026-04/27/content_3191574.html",
          "meta": "zbnews.net"
        },
        {
          "rank": 4,
          "title": "检修改造保供电",
          "url": "http://www.zbnews.net/content/2026-04/26/content_3191519.html",
          "meta": "zbnews.net"
        },
        {
          "rank": 5,
          "title": "茶树管护忙",
          "url": "http://www.zbnews.net/content/2026-04/24/content_3191378.html",
          "meta": "zbnews.net"
        }
      ]
    },
    {
      "key": "province",
      "title": "省级媒体里的淄博",
      "items": [
        {
          "rank": 1,
          "title": "好客山东燃情 _淄博_ 厚植融合发展优势",
          "url": "https://baijiahao.baidu.com/s?id=1863770562488909836&wfr=spider&for=pc",
          "meta": "baijiahao.baidu.com"
        },
        {
          "rank": 2,
          "title": "五一假期临近 _淄博_ 博山交警送教进课堂",
          "url": "https://baijiahao.baidu.com/s?id=1863775915719535020&wfr=spider&for=pc",
          "meta": "baijiahao.baidu.com"
        },
        {
          "rank": 3,
          "title": "淄博_ 9人(集体)荣获全国五一劳动奖表彰",
          "url": "http://news.10jqka.com.cn/20260429/c676363720.shtml",
          "meta": "news.10jqka.com.cn"
        },
        {
          "rank": 4,
          "title": "淄博_ 傅山地质博物馆人气爆棚,亲子研学热掀起科普新风尚",
          "url": "https://baijiahao.baidu.com/s?id=1863762572627204747&wfr=spider&for=pc",
          "meta": "baijiahao.baidu.com"
        },
        {
          "rank": 5,
          "title": "淄博_ 海关联合科技局举办政策宣讲会 助力科创企业降本增效",
          "url": "http://news.10jqka.com.cn/20260429/c676363692.shtml",
          "meta": "news.10jqka.com.cn"
        },
        {
          "rank": 6,
          "title": "属于 _淄博_ 的浪漫!城市书房藏烟火,一缕书香润全城",
          "url": "https://baijiahao.baidu.com/s?id=1863766251190361646&wfr=spider&for=pc",
          "meta": "baijiahao.baidu.com"
        },
        {
          "rank": 7,
          "title": "五一暖心护航丨山东移动 _淄博_ 分公司赋能城市奋斗者",
          "url": "https://baijiahao.baidu.com/s?id=1863773300032895706&wfr=spider&for=pc",
          "meta": "baijiahao.baidu.com"
        },
        {
          "rank": 8,
          "title": "以赛育才 _淄博_ 陶琉匠人同台竞技激活产业新动能",
          "url": "https://baijiahao.baidu.com/s?id=1863718730429299740&wfr=spider&for=pc",
          "meta": "baijiahao.baidu.com"
        }
      ]
    }
  ]
}
