{
  "source": "zibo",
  "updatedAt": "2026-05-16T10:21:59.637Z",
  "count": 14,
  "items": [
    {
      "rank": 1,
      "title": "赶订单 生产忙",
      "url": "http://www.zbnews.net/content/2026-05/15/content_3192646.html",
      "meta": "zbnews.net"
    },
    {
      "rank": 2,
      "title": "交管机器人在杭州街头“上岗”",
      "url": "http://www.zbnews.net/content/2026-05/13/content_3192526.html",
      "meta": "zbnews.net"
    },
    {
      "rank": 3,
      "title": "“善小”科普进校园",
      "url": "http://www.zbnews.net/content/2026-05/12/content_3192450.html",
      "meta": "zbnews.net"
    },
    {
      "rank": 4,
      "title": "“淄博好礼”绽芳华",
      "url": "http://www.zbnews.net/content/2026-05/12/content_3192370.html",
      "meta": "zbnews.net"
    },
    {
      "rank": 5,
      "title": "5:0淄博队开门红",
      "url": "http://www.zbnews.net/content/2026-05/11/content_3192307.html",
      "meta": "zbnews.net"
    },
    {
      "rank": 1,
      "title": "文旅融合激活振兴动能 _淄博_ 淄川杏山绘就乡村旅游富民新画卷",
      "url": "https://baijiahao.baidu.com/s?id=1865240561405273253&wfr=spider&for=pc",
      "meta": "baijiahao.baidu.com"
    },
    {
      "rank": 2,
      "title": "淄博_ 如何为青年幸福“搭桥”",
      "url": "https://baijiahao.baidu.com/s?id=1865217126224487968&wfr=spider&for=pc",
      "meta": "baijiahao.baidu.com"
    },
    {
      "rank": 3,
      "title": "山东省暨 _淄博市_ 第二十三届社会科学普及周启幕",
      "url": "https://baijiahao.baidu.com/s?id=1865258176865930875&wfr=spider&for=pc",
      "meta": "baijiahao.baidu.com"
    },
    {
      "rank": 4,
      "title": "山东理工大学与 _淄博市_ 校城融合十年结硕果 “一人双岗”计划破解...",
      "url": "http://news.10jqka.com.cn/20260516/c676741860.shtml",
      "meta": "news.10jqka.com.cn"
    },
    {
      "rank": 5,
      "title": "淄博_ 一公司客服多次辱骂客户被辞退,员工申请仲裁要求公司赔偿...",
      "url": "https://baijiahao.baidu.com/s?id=1865329544296903900&wfr=spider&for=pc",
      "meta": "baijiahao.baidu.com"
    },
    {
      "rank": 6,
      "title": "技改破局 _淄博_ 智造向高而攀",
      "url": "https://baijiahao.baidu.com/s?id=1864947379854643021&wfr=spider&for=pc",
      "meta": "baijiahao.baidu.com"
    },
    {
      "rank": 7,
      "title": "十家单位入选首批 _淄博市_ 工程师工作站",
      "url": "https://baijiahao.baidu.com/s?id=1865142290188952507&wfr=spider&for=pc",
      "meta": "baijiahao.baidu.com"
    },
    {
      "rank": 8,
      "title": "涉及招生划片等问题,_淄博_ 一地最新说明!",
      "url": "https://baijiahao.baidu.com/s?id=1865329793015755956&wfr=spider&for=pc",
      "meta": "baijiahao.baidu.com"
    },
    {
      "rank": 9,
      "title": "淄博市_ 首批工程师工作站设立",
      "url": "https://baijiahao.baidu.com/s?id=1864980506143152411&wfr=spider&for=pc",
      "meta": "baijiahao.baidu.com"
    }
  ],
  "sections": [
    {
      "key": "local",
      "title": "淄博新闻网",
      "items": [
        {
          "rank": 1,
          "title": "赶订单 生产忙",
          "url": "http://www.zbnews.net/content/2026-05/15/content_3192646.html",
          "meta": "zbnews.net"
        },
        {
          "rank": 2,
          "title": "交管机器人在杭州街头“上岗”",
          "url": "http://www.zbnews.net/content/2026-05/13/content_3192526.html",
          "meta": "zbnews.net"
        },
        {
          "rank": 3,
          "title": "“善小”科普进校园",
          "url": "http://www.zbnews.net/content/2026-05/12/content_3192450.html",
          "meta": "zbnews.net"
        },
        {
          "rank": 4,
          "title": "“淄博好礼”绽芳华",
          "url": "http://www.zbnews.net/content/2026-05/12/content_3192370.html",
          "meta": "zbnews.net"
        },
        {
          "rank": 5,
          "title": "5:0淄博队开门红",
          "url": "http://www.zbnews.net/content/2026-05/11/content_3192307.html",
          "meta": "zbnews.net"
        }
      ]
    },
    {
      "key": "province",
      "title": "省级媒体里的淄博",
      "items": [
        {
          "rank": 1,
          "title": "文旅融合激活振兴动能 _淄博_ 淄川杏山绘就乡村旅游富民新画卷",
          "url": "https://baijiahao.baidu.com/s?id=1865240561405273253&wfr=spider&for=pc",
          "meta": "baijiahao.baidu.com"
        },
        {
          "rank": 2,
          "title": "淄博_ 如何为青年幸福“搭桥”",
          "url": "https://baijiahao.baidu.com/s?id=1865217126224487968&wfr=spider&for=pc",
          "meta": "baijiahao.baidu.com"
        },
        {
          "rank": 3,
          "title": "山东省暨 _淄博市_ 第二十三届社会科学普及周启幕",
          "url": "https://baijiahao.baidu.com/s?id=1865258176865930875&wfr=spider&for=pc",
          "meta": "baijiahao.baidu.com"
        },
        {
          "rank": 4,
          "title": "山东理工大学与 _淄博市_ 校城融合十年结硕果 “一人双岗”计划破解...",
          "url": "http://news.10jqka.com.cn/20260516/c676741860.shtml",
          "meta": "news.10jqka.com.cn"
        },
        {
          "rank": 5,
          "title": "淄博_ 一公司客服多次辱骂客户被辞退,员工申请仲裁要求公司赔偿...",
          "url": "https://baijiahao.baidu.com/s?id=1865329544296903900&wfr=spider&for=pc",
          "meta": "baijiahao.baidu.com"
        },
        {
          "rank": 6,
          "title": "技改破局 _淄博_ 智造向高而攀",
          "url": "https://baijiahao.baidu.com/s?id=1864947379854643021&wfr=spider&for=pc",
          "meta": "baijiahao.baidu.com"
        },
        {
          "rank": 7,
          "title": "十家单位入选首批 _淄博市_ 工程师工作站",
          "url": "https://baijiahao.baidu.com/s?id=1865142290188952507&wfr=spider&for=pc",
          "meta": "baijiahao.baidu.com"
        },
        {
          "rank": 8,
          "title": "涉及招生划片等问题,_淄博_ 一地最新说明!",
          "url": "https://baijiahao.baidu.com/s?id=1865329793015755956&wfr=spider&for=pc",
          "meta": "baijiahao.baidu.com"
        },
        {
          "rank": 9,
          "title": "淄博市_ 首批工程师工作站设立",
          "url": "https://baijiahao.baidu.com/s?id=1864980506143152411&wfr=spider&for=pc",
          "meta": "baijiahao.baidu.com"
        }
      ]
    }
  ]
}
