{
  "source": "zibo",
  "updatedAt": "2026-03-31T22:01:33.173Z",
  "count": 14,
  "items": [
    {
      "rank": 1,
      "title": "共守护 助成长",
      "url": "http://www.zbnews.net/content/2026-03/31/content_3189875.html",
      "meta": "zbnews.net"
    },
    {
      "rank": 2,
      "title": "全民健身 “乒”出精彩",
      "url": "http://www.zbnews.net/content/2026-03/30/content_3189821.html",
      "meta": "zbnews.net"
    },
    {
      "rank": 3,
      "title": "时尚创意 青春市集",
      "url": "http://www.zbnews.net/content/2026-03/29/content_3189772.html",
      "meta": "zbnews.net"
    },
    {
      "rank": 4,
      "title": "跃动童年",
      "url": "http://www.zbnews.net/content/2026-03/28/content_3189717.html",
      "meta": "zbnews.net"
    },
    {
      "rank": 5,
      "title": "新城水库连续多年迎来北归天鹅",
      "url": "http://www.zbnews.net/content/2026-03/27/content_3189661.html",
      "meta": "zbnews.net"
    },
    {
      "rank": 1,
      "title": "淄博市_ 淄川区举行第二批退役军人研学站发布会暨志愿服务队授旗仪式",
      "url": "https://baijiahao.baidu.com/s?id=1861184743174120826&wfr=spider&for=pc",
      "meta": "baijiahao.baidu.com"
    },
    {
      "rank": 2,
      "title": "淄博_ 博山:春花经济促乡村振兴",
      "url": "https://baijiahao.baidu.com/s?id=1861188142767064218&wfr=spider&for=pc",
      "meta": "baijiahao.baidu.com"
    },
    {
      "rank": 3,
      "title": "恶意碰瓷三十余起 _淄博_ 警方依法刑拘嫌疑人",
      "url": "https://baijiahao.baidu.com/s?id=1861162061422933657&wfr=spider&for=pc",
      "meta": "baijiahao.baidu.com"
    },
    {
      "rank": 4,
      "title": "山东省 _淄博市_ 第十中学举行“清明节”主题升旗仪式",
      "url": "https://baijiahao.baidu.com/s?id=1861184869150445648&wfr=spider&for=pc",
      "meta": "baijiahao.baidu.com"
    },
    {
      "rank": 5,
      "title": "淄博_ 工贸学校:深化产教融合 精准对接产业",
      "url": "https://baijiahao.baidu.com/s?id=1861185309565328126&wfr=spider&for=pc",
      "meta": "baijiahao.baidu.com"
    },
    {
      "rank": 6,
      "title": "2026年 _淄博市_ 交通建设工作会议召开",
      "url": "https://baijiahao.baidu.com/s?id=1861198294646014577&wfr=spider&for=pc",
      "meta": "baijiahao.baidu.com"
    },
    {
      "rank": 7,
      "title": "逛聊斋故里·赏陶风琉韵 _淄博_ 淄川邀你解锁春日文旅新体验",
      "url": "https://baijiahao.baidu.com/s?id=1861163705210094712&wfr=spider&for=pc",
      "meta": "baijiahao.baidu.com"
    },
    {
      "rank": 8,
      "title": "淄博_:2026年首场“中国工人大思政课”开讲",
      "url": "https://baijiahao.baidu.com/s?id=1861166874868407152&wfr=spider&for=pc",
      "meta": "baijiahao.baidu.com"
    },
    {
      "rank": 9,
      "title": "好客山东 燃情 _淄博_|打扮好看就能免票!淄博花灯齐彩城春日福利刷屏",
      "url": "https://baijiahao.baidu.com/s?id=1861167472808916240&wfr=spider&for=pc",
      "meta": "baijiahao.baidu.com"
    }
  ],
  "sections": [
    {
      "key": "local",
      "title": "淄博新闻网",
      "items": [
        {
          "rank": 1,
          "title": "共守护 助成长",
          "url": "http://www.zbnews.net/content/2026-03/31/content_3189875.html",
          "meta": "zbnews.net"
        },
        {
          "rank": 2,
          "title": "全民健身 “乒”出精彩",
          "url": "http://www.zbnews.net/content/2026-03/30/content_3189821.html",
          "meta": "zbnews.net"
        },
        {
          "rank": 3,
          "title": "时尚创意 青春市集",
          "url": "http://www.zbnews.net/content/2026-03/29/content_3189772.html",
          "meta": "zbnews.net"
        },
        {
          "rank": 4,
          "title": "跃动童年",
          "url": "http://www.zbnews.net/content/2026-03/28/content_3189717.html",
          "meta": "zbnews.net"
        },
        {
          "rank": 5,
          "title": "新城水库连续多年迎来北归天鹅",
          "url": "http://www.zbnews.net/content/2026-03/27/content_3189661.html",
          "meta": "zbnews.net"
        }
      ]
    },
    {
      "key": "province",
      "title": "省级媒体里的淄博",
      "items": [
        {
          "rank": 1,
          "title": "淄博市_ 淄川区举行第二批退役军人研学站发布会暨志愿服务队授旗仪式",
          "url": "https://baijiahao.baidu.com/s?id=1861184743174120826&wfr=spider&for=pc",
          "meta": "baijiahao.baidu.com"
        },
        {
          "rank": 2,
          "title": "淄博_ 博山:春花经济促乡村振兴",
          "url": "https://baijiahao.baidu.com/s?id=1861188142767064218&wfr=spider&for=pc",
          "meta": "baijiahao.baidu.com"
        },
        {
          "rank": 3,
          "title": "恶意碰瓷三十余起 _淄博_ 警方依法刑拘嫌疑人",
          "url": "https://baijiahao.baidu.com/s?id=1861162061422933657&wfr=spider&for=pc",
          "meta": "baijiahao.baidu.com"
        },
        {
          "rank": 4,
          "title": "山东省 _淄博市_ 第十中学举行“清明节”主题升旗仪式",
          "url": "https://baijiahao.baidu.com/s?id=1861184869150445648&wfr=spider&for=pc",
          "meta": "baijiahao.baidu.com"
        },
        {
          "rank": 5,
          "title": "淄博_ 工贸学校:深化产教融合 精准对接产业",
          "url": "https://baijiahao.baidu.com/s?id=1861185309565328126&wfr=spider&for=pc",
          "meta": "baijiahao.baidu.com"
        },
        {
          "rank": 6,
          "title": "2026年 _淄博市_ 交通建设工作会议召开",
          "url": "https://baijiahao.baidu.com/s?id=1861198294646014577&wfr=spider&for=pc",
          "meta": "baijiahao.baidu.com"
        },
        {
          "rank": 7,
          "title": "逛聊斋故里·赏陶风琉韵 _淄博_ 淄川邀你解锁春日文旅新体验",
          "url": "https://baijiahao.baidu.com/s?id=1861163705210094712&wfr=spider&for=pc",
          "meta": "baijiahao.baidu.com"
        },
        {
          "rank": 8,
          "title": "淄博_:2026年首场“中国工人大思政课”开讲",
          "url": "https://baijiahao.baidu.com/s?id=1861166874868407152&wfr=spider&for=pc",
          "meta": "baijiahao.baidu.com"
        },
        {
          "rank": 9,
          "title": "好客山东 燃情 _淄博_|打扮好看就能免票!淄博花灯齐彩城春日福利刷屏",
          "url": "https://baijiahao.baidu.com/s?id=1861167472808916240&wfr=spider&for=pc",
          "meta": "baijiahao.baidu.com"
        }
      ]
    }
  ]
}
